{
 "cells": [
  {
   "cell_type": "code",
   "execution_count": 1,
   "id": "c770b26a",
   "metadata": {},
   "outputs": [],
   "source": [
    "import numpy as np\n",
    "from heapq import heappush, heappop\n",
    "from numba import njit, prange, boolean\n",
    "from numba.core import types\n",
    "from numba.typed import Dict"
   ]
  },
  {
   "cell_type": "code",
   "execution_count": 2,
   "id": "94fcf06b",
   "metadata": {},
   "outputs": [],
   "source": [
    "float_array = types.f8[:]\n",
    "@njit(parallel=True)\n",
    "def gen_graph_compiled(nverts=3e3, dims=3):\n",
    "    vertices = np.array([(np.float64(0),np.float64(0),np.float64(0))]*nverts)\n",
    "    for i in prange(nverts):\n",
    "        vertices[i] = np.random.uniform(0, 1, dims)\n",
    "    return vertices\n",
    "        "
   ]
  },
  {
   "cell_type": "code",
   "execution_count": 3,
   "id": "437a94b5",
   "metadata": {},
   "outputs": [],
   "source": [
    "int_array = types.i8[:]\n",
    "@njit\n",
    "def choose_edges_compiled(vertices: Dict, min_connections=2, max_connections=-1):\n",
    "    edges = Dict.empty(\n",
    "        key_type = types.i8,\n",
    "        value_type = int_array\n",
    "    )\n",
    "    for i in range(len(vertices)):\n",
    "        other_verts = np.array(list(range(len(vertices))))\n",
    "        nedges = min_connections\n",
    "        these_edges = np.random.choice(other_verts, nedges, replace=False)\n",
    "        edges[i] = these_edges\n",
    "        for j in these_edges:\n",
    "            if (j in list(edges.keys())):\n",
    "                edges[j] = np.concatenate((edges[j],np.array([i])))\n",
    "            else:\n",
    "                edges[j] = np.array([i])\n",
    "\n",
    "    return edges\n",
    "    "
   ]
  },
  {
   "cell_type": "code",
   "execution_count": 4,
   "id": "0a7111db",
   "metadata": {},
   "outputs": [],
   "source": [
    "def get_mindist(dist, Q):\n",
    "    dists = np.empty(len(dist), np.float64)\n",
    "    for i in range(dists.shape[0]):\n",
    "        a = boolean(i in Q)\n",
    "        dists[i] = dist[i] * a + np.float64(1e9) * (1-a)\n",
    "    return np.argmin(dists)\n",
    "            \n",
    "\n",
    "def dijkstra_p(verts, edges, source, target):\n",
    "    dist = {}\n",
    "    prev = {}\n",
    "    Q = list(range(len(verts)))\n",
    "    for v in Q:\n",
    "        dist[v] = np.float64(1e9)\n",
    "        prev[v] = -1\n",
    "    dist[source] = 0\n",
    "    while len(Q):\n",
    "        u = get_mindist(dist, Q)\n",
    "        Q.remove(u)\n",
    "        if u == target:\n",
    "            return dist, prev\n",
    "        for i in range(len(edges[u])):\n",
    "            v = edges[u][i]\n",
    "            alt = dist[u] + np.linalg.norm(verts[u] - verts[v])\n",
    "            a = boolean(alt < dist[v])\n",
    "            dist[v] = alt * a + dist[v] * (1-a)\n",
    "            prev[v] = u * a + prev[v] * (1-a)\n",
    "    return dist, prev"
   ]
  },
  {
   "cell_type": "code",
   "execution_count": 5,
   "id": "efbdb433",
   "metadata": {},
   "outputs": [],
   "source": [
    "@njit\n",
    "def get_mindist_c(dist, Q):\n",
    "    dists = np.empty(len(dist), np.float64)\n",
    "    for i in range(dists.shape[0]):\n",
    "        a = boolean(i in Q)\n",
    "        dists[i] = dist[i] * a + np.float64(1e9) * (1-a)\n",
    "    return np.int64(np.argmin(dists))\n",
    "\n",
    "@njit\n",
    "def dijkstra_c(verts, edges, source, target):\n",
    "    dist = Dict.empty(\n",
    "        key_type = types.i8,\n",
    "        value_type = types.f8\n",
    "    )\n",
    "    prev = Dict.empty(\n",
    "        key_type = types.i8,\n",
    "        value_type = types.i8\n",
    "    )\n",
    "    Q = list(range(len(verts)))\n",
    "    for v in Q:\n",
    "        dist[v] = np.float(1e9)\n",
    "        prev[v] = np.int64(-1)\n",
    "    dist[source] = 0\n",
    "    while len(Q):\n",
    "        u = get_mindist_c(dist, Q)\n",
    "        Q.remove(u)\n",
    "        if u == target:\n",
    "            return dist, prev\n",
    "        for i in range(len(edges[u])):\n",
    "            v = edges[u][i]\n",
    "            alt = dist[u] + np.linalg.norm(verts[u] - verts[v])\n",
    "            a = boolean(alt < dist[v])\n",
    "            dist[v] = alt * a + dist[v] * (1-a)\n",
    "            prev[v] = u * a + prev[v] * (1-a)\n",
    "    return dist, prev"
   ]
  },
  {
   "cell_type": "code",
   "execution_count": 6,
   "id": "d66d741e",
   "metadata": {},
   "outputs": [],
   "source": [
    "@njit(parallel=True)\n",
    "def get_mindist_cp(dist, Q):\n",
    "    dists = np.empty(len(dist), np.float64)\n",
    "    for i in prange(dists.shape[0]):\n",
    "        a = boolean(i in Q)\n",
    "        dists[i] = dist[i] * a + np.float64(1e9) * (1-a)\n",
    "    return np.int64(np.argmin(dists))\n",
    "\n",
    "@njit(parallel=True)\n",
    "def dijkstra_cp(verts, edges, source, target):\n",
    "    dist = Dict.empty(\n",
    "        key_type = types.i8,\n",
    "        value_type = types.f8\n",
    "    )\n",
    "    prev = Dict.empty(\n",
    "        key_type = types.i8,\n",
    "        value_type = types.i8\n",
    "    )\n",
    "    Q = list(range(len(verts)))\n",
    "    for v in Q:\n",
    "        dist[v] = np.float(1e9)\n",
    "        prev[v] = np.int64(-1)\n",
    "    dist[source] = 0\n",
    "    while len(Q):\n",
    "        u = get_mindist_cp(dist, Q)\n",
    "        Q.remove(u)\n",
    "        if u == target:\n",
    "            return dist, prev\n",
    "        for i in prange(len(edges[u])):\n",
    "            v = edges[u][i]\n",
    "            alt = dist[u] + np.linalg.norm(verts[u] - verts[v])\n",
    "            a = boolean(alt < dist[v])\n",
    "            dist[v] = alt * a + dist[v] * (1-a)\n",
    "            prev[v] = u * a + prev[v] * (1-a)\n",
    "    return dist, prev"
   ]
  },
  {
   "cell_type": "code",
   "execution_count": 7,
   "id": "a4daf2a2",
   "metadata": {},
   "outputs": [],
   "source": [
    "def dijkstra_pq(verts, edges, source, target):\n",
    "    dist = np.array([1e9]*(len(verts)))\n",
    "    prev = np.array([-1]*(len(verts)))\n",
    "    dist[source] = 0\n",
    "    Q = [(0, source)]\n",
    "    while len(Q):\n",
    "        u = heappop(Q)[1]\n",
    "        if u == target:\n",
    "            return dist, prev\n",
    "        for v in edges[u]:\n",
    "            alt = dist[u] + np.linalg.norm(verts[u] - verts[v])\n",
    "            if alt < dist[v]:\n",
    "                dist[v] = alt\n",
    "                prev[v] = u\n",
    "                heappush(Q, (dist[v], v))\n",
    "    return dist, prev"
   ]
  },
  {
   "cell_type": "code",
   "execution_count": 8,
   "id": "8b0e75b5",
   "metadata": {},
   "outputs": [],
   "source": [
    "@njit\n",
    "def dijkstra_cq(verts, edges, source, target):\n",
    "    dist = np.array([np.float64(1e9)]*(len(verts)))\n",
    "    prev = np.array([-1]*(len(verts)))\n",
    "    dist[source] = np.float64(0)\n",
    "    Q = [(np.float64(0), source)]\n",
    "    while len(Q):\n",
    "        u = heappop(Q)[1]\n",
    "        if u == target:\n",
    "            return dist, prev\n",
    "        for v in edges[u]:\n",
    "            alt = dist[u] + np.linalg.norm(verts[u] - verts[v])\n",
    "            if alt < dist[v]:\n",
    "                dist[v] = alt\n",
    "                prev[v] = u\n",
    "                heappush(Q, (dist[v], v))\n",
    "    return dist, prev"
   ]
  },
  {
   "cell_type": "code",
   "execution_count": 9,
   "id": "2bae9898",
   "metadata": {},
   "outputs": [],
   "source": [
    "def path_dijkstra(prev, source, target):\n",
    "    s = []\n",
    "    u = target\n",
    "    while u != source:\n",
    "        s.append(u)\n",
    "        u = prev[u]\n",
    "    s.append(source)\n",
    "    return s"
   ]
  },
  {
   "cell_type": "code",
   "execution_count": 10,
   "id": "2847b07f",
   "metadata": {},
   "outputs": [
    {
     "name": "stdout",
     "output_type": "stream",
     "text": [
      "Simulating 10 3d vertices within unit cube with random edges\n",
      "Source vertex: 5, [0.43226127 0.73096348 0.92281141]\n",
      "Target vertex: 0, [0.88383938 0.49621293 0.58717894]\n"
     ]
    },
    {
     "name": "stderr",
     "output_type": "stream",
     "text": [
      "<ipython-input-6-eaf88cfb7be7>:25: NumbaTypeSafetyWarning: \u001b[1m\u001b[1m\u001b[1m\u001b[1munsafe cast from uint64 to int64. Precision may be lost.\u001b[0m\u001b[0m\u001b[0m\u001b[0m\n",
      "  u = get_mindist_cp(dist, Q)\n"
     ]
    },
    {
     "name": "stdout",
     "output_type": "stream",
     "text": [
      "Simulating 10 3d vertices within unit cube with random edges\n",
      "Source vertex: 5, [0.34915352 0.02739964 0.83578147]\n",
      "Target vertex: 2, [0.79813465 0.00807183 0.01978186]\n",
      "Simulating 30 3d vertices within unit cube with random edges\n",
      "Source vertex: 13, [0.51758632 0.57363084 0.32295542]\n",
      "Target vertex: 4, [0.34669025 0.38607887 0.49504221]\n",
      "Simulating 100 3d vertices within unit cube with random edges\n",
      "Source vertex: 82, [0.12049545 0.02486669 0.43940189]\n",
      "Target vertex: 10, [0.08420694 0.07081778 0.03095456]\n",
      "Simulating 300 3d vertices within unit cube with random edges\n",
      "Source vertex: 69, [0.12739859 0.60118627 0.37627365]\n",
      "Target vertex: 135, [0.07579184 0.87438011 0.26272206]\n",
      "Simulating 1000 3d vertices within unit cube with random edges\n",
      "Source vertex: 237, [0.3923855  0.89373256 0.08428274]\n",
      "Target vertex: 587, [0.25558778 0.64577896 0.14927144]\n",
      "Simulating 3000 3d vertices within unit cube with random edges\n",
      "Source vertex: 465, [0.28746267 0.332124   0.8776043 ]\n",
      "Target vertex: 515, [0.03483424 0.083681   0.07925194]\n",
      "Simulating 10000 3d vertices within unit cube with random edges\n",
      "Source vertex: 7462, [0.81719761 0.47202719 0.66410838]\n",
      "Target vertex: 5338, [0.58366773 0.1316149  0.98642095]\n"
     ]
    }
   ],
   "source": [
    "from time import perf_counter_ns\n",
    "vertex_choices = [10, 10, 30, 100, 300, 1000, 3000, 10000]\n",
    "times_p = []\n",
    "times_c = []\n",
    "times_cp = []\n",
    "times_pq = []\n",
    "times_cq = []\n",
    "for choice in vertex_choices:\n",
    "    print(f'Simulating {choice} 3d vertices within unit cube with random edges')\n",
    "    vert = gen_graph_compiled(choice)\n",
    "    edge = choose_edges_compiled(vert)\n",
    "    source, target = np.random.choice(list(range(len(vert))), 2, False)\n",
    "    print(f'Source vertex: {source}, {vert[source]}')\n",
    "    print(f'Target vertex: {target}, {vert[target]}')\n",
    "    start_p = perf_counter_ns()\n",
    "    dist_p, prev_p = dijkstra_p(vert, edge, source, target)\n",
    "    times_p.append((perf_counter_ns() - start_p)/1e6)\n",
    "    start_c = perf_counter_ns()\n",
    "    dist_c, prev_c = dijkstra_c(vert, edge, source, target)\n",
    "    times_c.append((perf_counter_ns() - start_c)/1e6)\n",
    "    start_cp = perf_counter_ns()\n",
    "    dist_cp, prev_cp = dijkstra_cp(vert, edge, source, target)\n",
    "    times_cp.append((perf_counter_ns() - start_c)/1e6)\n",
    "    start_pq = perf_counter_ns()\n",
    "    dist_pq, prev_pq = dijkstra_pq(vert, edge, source, target)\n",
    "    times_pq.append((perf_counter_ns() - start_pq)/1e6)\n",
    "    start_cq = perf_counter_ns()\n",
    "    dist_cq, prev_cq = dijkstra_cq(vert, edge, source, target)\n",
    "    times_cq.append((perf_counter_ns() - start_cq)/1e6)\n",
    "    "
   ]
  },
  {
   "cell_type": "code",
   "execution_count": 11,
   "id": "279f1bdc",
   "metadata": {},
   "outputs": [],
   "source": [
    "path_p = path_dijkstra(prev_p, source, target)\n",
    "path_pq = path_dijkstra(prev_pq, source, target)\n",
    "path_cq = path_dijkstra(prev_cq, source, target)\n",
    "path_c = path_dijkstra(prev_c, source, target)\n",
    "path_cp = path_dijkstra(prev_cp, source, target)"
   ]
  },
  {
   "cell_type": "code",
   "execution_count": 12,
   "id": "740854f9",
   "metadata": {},
   "outputs": [],
   "source": [
    "def path_distance(path, vertices:np.array):\n",
    "    source = path[0]\n",
    "    dist = 0\n",
    "    for i, x in enumerate(path):\n",
    "        if i == 0:\n",
    "            continue\n",
    "        else:\n",
    "            dist += np.linalg.norm(vertices[path[i]] - vertices[path[i-1]])\n",
    "    return dist"
   ]
  },
  {
   "cell_type": "code",
   "execution_count": 13,
   "id": "56170a18",
   "metadata": {},
   "outputs": [],
   "source": [
    "paths = [globals()[f'path_{f}'] for f in ['p', 'pq', 'cq', 'c', 'cp']]"
   ]
  },
  {
   "cell_type": "code",
   "execution_count": 14,
   "id": "7794539b",
   "metadata": {},
   "outputs": [],
   "source": [
    "for i, x in enumerate(paths):\n",
    "    assert paths[i] == paths[0]"
   ]
  },
  {
   "cell_type": "code",
   "execution_count": 15,
   "id": "1b9e57bf",
   "metadata": {},
   "outputs": [
    {
     "data": {
      "text/plain": [
       "3.3997492150622075"
      ]
     },
     "execution_count": 15,
     "metadata": {},
     "output_type": "execute_result"
    }
   ],
   "source": [
    "path_distance(path_p, vert)"
   ]
  },
  {
   "cell_type": "code",
   "execution_count": 16,
   "id": "b376939b",
   "metadata": {},
   "outputs": [],
   "source": [
    "import matplotlib.pyplot as plt\n",
    "from sklearn.linear_model import LinearRegression\n",
    "\n",
    "def time_regression(nverts, times, c):\n",
    "    X = np.vstack((np.array(np.log(nverts)),np.array([np.log(x)**2 for x in nverts]))).T\n",
    "    lm = LinearRegression().fit(X[1:], np.log(times[1:]))\n",
    "    predict = lm.predict(X[1:])\n",
    "    plt.plot(X[1:,0], predict, c, ls='--')\n",
    "    #plt.plot(X[1:,0], np.log(times[1:]), c, ls='-')\n",
    "    return predict\n",
    "    "
   ]
  },
  {
   "cell_type": "code",
   "execution_count": 17,
   "id": "9ad02604",
   "metadata": {},
   "outputs": [
    {
     "name": "stdout",
     "output_type": "stream",
     "text": [
      "3254.3658781360277\n"
     ]
    },
    {
     "data": {
      "image/png": "iVBORw0KGgoAAAANSUhEUgAAAlsAAAI/CAYAAABAoBw9AAAAOXRFWHRTb2Z0d2FyZQBNYXRwbG90bGliIHZlcnNpb24zLjMuNCwgaHR0cHM6Ly9tYXRwbG90bGliLm9yZy8QVMy6AAAACXBIWXMAAAsTAAALEwEAmpwYAACL60lEQVR4nOzddXyV5f/H8de9sQ5G50Y3SI0SkEZBGikFCQURsLv1Z/u1scAECUVUQqS7YaQ0SHcOGKzP/fvjAjFAgZ3tPufs/Xw89thO3h+YbG+v+FyWbduIiIiISObwc7oAEREREV+msCUiIiKSiRS2RERERDKRwpaIiIhIJlLYEhEREclEClsiIiIimSiH0wX8m7x589rFixd3ugwRERGR/7Rq1arjtm3n+/v9Hh22ihcvTlxcnNNliIiIiPwny7L2XO5+TSOKiIiIZCKFLREREZFMpLAlIiIikokUtkREREQykcKWiIiISCZS2BIRERHJRApbIiIiIplIYUtEREQkEylsiYiIiGQihS0RERGRTKSwJSIiIpKJFLZEREREMpHCloiIiEgmuuqwZVnWV5ZlHbUsa8Of7vufZVlbLMtab1nWz5ZlRV3htbsty/rNsqy1lmXFuaFuEREREa9wLSNb3wC3/O2+mUBl27ZvALYBT/3L65vYtl3Ntu3YaytRRERExHtdddiybXsBcPJv982wbTvtws1lQFE31iYiIiLi9dy5ZqsfMPUKj9nADMuyVlmWNcCN1xQRERHxaDnc8SaWZT0DpAGjr/CU+rZtH7QsKz8w07KsLRdGyi73XgOAAQAxMTHuKE9ERETEMRke2bIsqzfQBrjDtm37cs+xbfvghc9HgZ+B2ld6P9u2h9u2HWvbdmy+fPkyWp6IiIiIozIUtizLugV4Amhn2/b5KzwnzLKsiItfAy2BDZd7roiIiIivuZbWD2OBpUA5y7L2W5Z1F/AREIGZGlxrWdZnF55b2LKsXy+8tACwyLKsdcAKYIpt29Pc+qcQERER8VBXvWbLtu0el7n7yys89yDQ+sLXO4Gq11WdiIiIiJdTB3kRERHxTenp8MEHcOaMo2W4ZTeiiIiIiEexbWjfHqZMgaAgGDjQsVIUtkRERMT3WBa0awcdO0K/fo6WorAlIiIivsHlgrfeglKloEsXGOAZfdS1ZktERES834kT0LYtPPUUzJzpdDV/oZEtERER8W5LlkC3bnD0KHzyiaPrsy5HYUtERES815Yt0KgRxMSY0FWzptMV/YOmEUVERMT7uFzmc/ny8PHHsGqVRwYtUNgSERERbxMXB1WqwLp15vaAARAV5WhJ/0ZhS0RERLyDbZtRrPr1ISEBUlKcruiqKGyJiIiI5ztzxiyCHzIEWrSA1auhVi2nq7oqClsiIiLi+T76CH76Cd58EyZNgjx5nK7oqmk3ooiIiHgm2zbtHAoUgMceg5YtITbW6aqumUa2RERExPMkJECvXiZcnTwJAQFeGbRAYUtEREQ8zcaNZj3WmDFmp2HOnE5XlCGaRhQRERHPMWIE3HsvRESYY3eaNXO6ogxT2BIRERHP4HKZ0azatWHsWChUyOmK3EJhS0RERJy1dSuEh0ORIjBuHISFQQ7fiShasyUiIiLOGTvWLHwfMsTczpnTp4IWKGyJiIiIE5KSzNqs22+HqlVh6FCnK8o0ClsiIiKStfbtgxtvhM8+M/2z5s6FokWdrirT+NY4nYiIiHi+yEgzVThpErRt63Q1mU4jWyIiIpL5UlLgf/8z04c5c8Ly5dkiaIHCloiIiGS2PXugYUN4/HGYPNncZ1nO1pSFFLZEREQk8/zyC1SvDlu2wPjx0KWL0xVlOYUtERERyRxDh5qpwuLFYfVq6NzZ6YocobAlIiIimaNlS7j/fliyBEqVcroaxyhsiYiIiPvMmGEClm1DuXLwwQcQHOx0VY5S2BIREZGMS0+H55+HW24xfbNOn3a6Io+hsCUiIiIZc/gwtGgBL78MffqYtg5RUU5X5THU1FRERESun8sFzZvDzp3w9dcmbMlfKGyJiIjItXO5zGc/P7Muq0ABqFzZ2Zo8lKYRRURE5NocOwatW8M775jbzZopaP0LhS0RERG5eosXmyal8+ZpXdZVUtgSERGR/2bb8Pbb0KgRhITA0qXQv7/TVXkFhS0RERH5b+vXwxNPQMeOEBdnRrfkqmiBvIiIiFzZwYNQuDBUrWpaOtSsma0OkXYHjWyJiIjIP9m22WVYsiTMnGnui41V0LoOGtkSERGRv4qPh7vugp9+gnbtTMiS66aRLREREblk9WozVThxolkQP2EC5MrldFVeTSNbIiIicsnSpZCSAgsWwI03Ol2NT9DIloiISHZ39iwsWWK+HjQINmxQ0HIjhS0REZHs7LffzJqsNm3gzBmzAD5nTqer8ikKWyIiItmRbcNXX0Ht2iZk/fwzREY6XZVPUtgSERHJbtLSoG9fs+Owfn1Yu9Z0hpdMobAlIiKS3eTIAUFB8MILMH06FCjgdEU+TbsRRUREsovRo6FKFbjhBvjsMzUozSIa2RIREfF1iYlwzz3Qsye89565T0Ery2hkS0RExJdt3w5dusC6dfDkk/Dyy05XlO0obImIiPiqNWvMwveAAJgyBVq3drqibEnTiCIiIr6qcmW4804TuhS0HKOwJSIi4kt27YJOneD4cTOi9dFHEBPjdFXZmsKWiIiIr5g4EWrUgDlzYPNmp6uRCxS2REREvF1qKjz6KHToAKVKwerV0LCh01XJBQpbIiIi3u7pp+Gdd2DwYFi8GEqWdLoi+RPtRhQREfFWqalmXdZjj0HdutC5s9MVyWVoZEtERMTbpKWZ0azmzc3X+fMraHkwhS0RERFvcvAgNGsGr78OZcqYsCUeTdOIIiIi3mLWLLj9djh3DkaOhF69nK5IroLCloiIiDdITYVBgyBfPpg3DypWdLoiuUoKWyIiIp7s6FGIjITgYHPkTuHCEBbmdFVyDbRmS0RExFMtWADVqsHjj5vbZcooaHmhqw5blmV9ZVnWUcuyNvzpvtyWZc20LGv7hc+5rvDaWyzL2mpZ1g7Lsp50R+EiIiI+y+WCN96AJk0gIgLuvtvpiiQDrmVk6xvglr/d9yQw27btMsDsC7f/wrIsf+BjoBVQEehhWZYmmkVERC7nxAlo2xaeegq6doW4OLjhBqerkgy46rBl2/YC4OTf7m4PjLjw9Qigw2VeWhvYYdv2Ttu2U4DvLrxORERE/u74cVi+HD75BMaMMSNb4tUyukC+gG3bhwBs2z5kWVb+yzynCLDvT7f3A3UyeF0RERHfYdvw66/QujWUKwe7dilk+ZCsWCBvXeY++4pPtqwBlmXFWZYVd+zYsUwsS0RExAOcOgWdOkGbNjBtmrlPQcunZDRsHbEsqxDAhc9HL/Oc/UD0n24XBQ5e6Q1t2x5u23asbdux+fLly2B5IiIiHmzlSqhZE375Bd57D275+9Jo8QUZDVuTgN4Xvu4NTLzMc1YCZSzLKmFZViDQ/cLrREREsq/PP4f69SE9HRYuhAcfBOtyk0Hi7a6l9cNYYClQzrKs/ZZl3QW8AbSwLGs70OLCbSzLKmxZ1q8Atm2nAUOA6cBmYJxt2xvd+8cQERHxMgULmjVaa9ZA3bpOVyOZyLLtKy6fclxsbKwdFxfndBkiIiLusWIFrF9/qW+WbWs0y4dYlrXKtu3Yv9+vDvIiIiKZzbbh/fehQQN4801ISjL3K2hlCwpbIiIimenUKejYER56yEwbrlhhzjmUbEMHUYuIiGSWxESoVQv27jW7DR94QKNZ2ZDCloiISGYJCYFHHjHtHWrXdroacYimEUVERNzp5EkzbXixQem99ypoZXMKWyIiIu6ybBlUrw5TpsD+/U5XIx5CYUtERCSjbBveeQcaNgQ/P1i8+FJ7B8n2FLZEREQy6pdf4NFHoV0706S0Vi2nKxIgzZXG/VPvZ/uJ7Y7WobAlIiJyvc6cMZ/btIHJk2H8eIiKcrQkuSQxNZGVB1cyc+dMR+tQ2BIREblWLhe8/TaUKAE7dph2Dm3aqK2Dh0h3pZOYmkhEUATz+8xnUK1Bjtaj1g8iIiLX4sQJ6NPHTB127gx58zpdkfxJuiudPhP7sG1zAG1cn/Pcs4FOl6SwJSIictWWLIHu3eHIERg6FAYP1miWB0l3pdNvUj9GjT9B0ISf2Rvpz8B7IF8+Z+tS2BIREblaI0dCQIAJXTVrOl2N/InLdnHXpLsZ+VlurJlfU7GqH5MmOR+0QGFLRETk3x0/bqYOy5WDd9+F1FTImdPpquRvnpj5BCNerw4r7qdjJ5OLw8KcrspQ2BIREbmSxYvNtGGuXLB2LYSGOl2RXEHf6n051HYbxZrbvPyyhZ8HbQFU2BIREfk7lwv+9z945hkoXhy++QaP+u0tgJk6/HjKXPKebUqPHhUZ9WxFp0u6LIUtERGRPzt9Gnr0gKlToUsX+PxzTRt6INu2aft/n/Dr673IlzuJDh1CCAlxuqrLU0wXERH5s9BQSEqCTz6B779X0PJALpfNTQN/5NeX7iV/0QTilgV7bNACjWyJiIiYacOhQ+GOO0zfrFmzNG3ooVwum6ptlrBh6m2Uqf8bq6dVJjzcs9tv6L8kERHJ3o4dg1tvhQcfNGuzQEHLg607spaN5+dQu/tMNs/3/KAFGtkSEZHsbOFCsz7r+HH49FO45x6nK5Ir2LwZ4uOhXr3qxI2B6oWqYXlJQ1mFLRERyZ5++MEErRIlYOlSqF7d6YrkCqZNs+nQOZkCRZLZtSUnNQp71/dK46QiIpI9NWpkRrJWrVLQ8lC2DR9+aNP6VpvkiC00e/Y9r5zh9cKSRURErtOCBdCtG6SlQf788PHHEBnpdFVyGWlpcO+9Ng88YGGXncjdH43gy14vOF3WdVHYEhER3+dywauvQpMmsGYNHDrkdEXyHyzLZu7GTdDgNfq/MZ1hnd/xmjVaf6c1WyIi4tuOHoVevWDGDLNGa9gwiIhwuiq5gi1bTKuz6Gi45ckvuSn9LJ+1HYaf5b3jQwpbIiLi2267DVasgOHD4e67wUtHR7KDGTOga1eoXjOFubMDeb/1O9jYXh20QNOIIiLii1wuSEkxX3/4ISxfDv37K2h5KNs2PWVbtYLgvEfYWLc++8/sx7Isrw9aoLAlIiK+5uhRuOUW06QUoFo1qFrVyYrkX6Smwr33wv33Q9l62zjStRS3xFagUHghp0tzG4UtERHxHfPmmXC1cKHaOXiJ5GTT5qzRHUvZ0qw8d8R24Ov2X+Pv5+90aW6jsCUiIt4vPR3+7/+gWTPTyuHitKF4rO3b4dw5CA+HBz//nvllbqTHDd0Z0WGETwUtUNgSERFfsHcvvPUW3H47xMXBDTc4XZH8i5kzoVYteOghc7tLtVt5pckrjOw40ueCFihsiYiIN9uwwayuLlEC1q2DkSPNUIl4rI8/NgvhY2Lghtt+ISElgfDAcJ656Rly+PlmkwSFLRER8T4Xpw2rVoUxY8x9pUppt6EHS02FwYNhyBATtnq+/yn3LW3LO0vecbq0TOebEVJERHzX4cNwxx0wZw707Ant2ztdkVyFw4dh3Dh47DEo2vFjHpgxhE4VOvF0w6edLi3TaWRLRES8x9y5Zrfh0qXw5ZeaNvQC+/ebmd7oaNi4EYp3+YQHZgyhY/mOfNf5OwL8A5wuMdMpbImIiPdISIA8eUxH+H79NG3o4WbPhipVzN4FgJCcZ3l14au0L9ee727LHkELFLZERMTTHT4MP/xgvm7bFtauhcqVHS1J/tunn8LNN0ORIuYIHoCIoAiW9FvCuC7jCPQPdLbALKSwJSIinmv2bDNtePfdcPKkuS8ge4yGeKu0NLMIftAg08h/yRKYc+pLHp7+MLZtUyyqWLYKWqCwJSIinig9HV54AVq0gNy5zW/s3Lmdrkquwrp1MGwYPPIITJwI43//iv6T+7P5+GZSXalOl+cI7UYUERHP4nKZIZFZs6BPH/joIwgLc7oq+Q+nT0POnFCzplkIX7YsfLP2G+6edDctSrXg524/Z7sRrYs0siUiIp7Fz88s9vn6a/OhoOXx5swxbc4mTDC3y5aFketG0m9iP5qXbM6EbhMIzhHsaI1OUtgSERHnpafD88/DtGnm9qOPmlEt8XjDhplsXKDAX09JigyK5JbStzCx+0RCAkKcK9ADKGyJiIizDh40B0i//LI5NE+8Qloa3H8/DBwILVua1mclS8KBMwcA6FC+A1Nun5LtgxYobImIiJNmzDC7DVeuhG++gXd8/+gWXzFlCgwdCg8/DJMmQWQkfL/he0p9WIqZv5vQbKkPGqAF8iIi4pQVK8xC+IoVzTkuFSs6XZFchZQUCAw0pyQtWgT165v7f9j4A3f8dAf1Y+pzY/SNzhbpYTSyJSIiWSstzXyuVQs++cSELgUtrzB3LpQpA+vXm9sXg9aPm36kx489qBddjym3TyEsUJsa/kxhS0REss6MGVC+POzYYY7aGTgQQkOdrkquwvDhZm1WWNhfN4huOLqB7j92p07ROvx6+6+EB+qsyr9T2BIRkcyXlgbPPmumDYODze5D8QppafDgg3DPPdC8uVkIX6rUpccr5avE0FZDmXrHVCKCIhyr05MpbImISOY6cACaNoVXXzWHR69YAeXKOV2VXKXPPoMPPjCBa/Jk07gUYMq2KWw8uhHLshgYO5DIoEhH6/RkWiAvIiKZ6513YPVq+PZb6NnT6WrkKtm2mem95x6IjjYL4i/6ZdsvdPq+EzeXvpnJPSY7V6SX0MiWiIi4X1oa7N9vvn71VRO2FLS8xvz5ULs2HDtmzv3+c9D6dfuvdB7XmaoFq/Jtx2+dK9KLKGyJiIh77d8PTZqYRqVJSRASYs5vEa/wxRdmbVZCgvn4s2k7ptHx+45Uzl+ZGT1nEBUc5UiN3kZhS0RE3GfaNKheHdauhRdeMIvhxSukp8NDD0H//iYnL10KJUpcety2bT5a8REV81VkZq+Z5ArJ5VyxXkZrtkREJOPS0szZhq+/bg7IGzdOi+C9zAsvwPvvmyN43nkHcvwpIdi2jWVZjOsyjqS0JHKH5HasTm+kkS0REck424Z582DAAFi2TEHLCz34IIwYYXYe/jlozd45m2Yjm3E66TShAaEKWtdBYUtERK7f9Olw/LhZRT17NgwbZtZoiVdYsAC6dDFH8OTNC3fe+dfH5+yaQ9uxbTl+/jiprlRnivQBClsiInLtUlLgscdMk9JXXjH3KWR5lS+/NAvhf/vN7Dr8u3m759FmTBtK5irJ7Dtnkzc0b9YX6SMUtkRE5Nrs2gUNG8Lbb8O995p1WuI10tPhkUfg7rvNptFly6BIkb8+Z9HeRdw65lZK5CrBnN5zyBeWz5lifYQWyIuIyNVbsADatTNrtMaNM3NQ4lUGDzazvffdB++++9f1WRcVCi9Eg5gGjOwwkvxh+bO+SB+jsCUiIlevfHlo1Ajeew9KlnS6GrkOgwaZ7hz33PPPx3ac3EHJXCUplbsU03tOz/rifJSmEUVE5N9t2wYDB5r2Dvnzw8SJClpeZuFCeOopMyB5ww2XD1pL9y2l+rDqvLLglawv0McpbImIyJWNHg01a8IPP5jQJV7n669Nk9KffoLTpy//nGX7l3HzqJspGF6Qu6rflbUFZgMZDluWZZWzLGvtnz7OWJb14N+e09iyrNN/es7zGb2uiIhkonPnoF8/c55htWqwbh1UrOh0VXIN0tPNhtF+/czM77JlEBX1z+etOLCCm0fdTP6w/MztPZcikUX++STJkAyv2bJteytQDcCyLH/gAPDzZZ660LbtNhm9noiIZIEePeCXX+CZZ+DFFy+/ilo8Ws+e8N13ZkH8e++ZVmh/dy7lHG3HtiVvaF7m9p5L0ciiWV9oNuDufz3NgN9t297j5vcVEZHMZttmOCRHDhOw7rsPWrRwuiq5Tl27QoMGJmxdSVhgGKM6jqJc3nJE54zOuuKyGXeHre7A2Cs8Vs+yrHXAQeBR27Y3uvnaIiJyvc6cMaumc+eGjz+GGjWcrkiuw6JFsGMH9OkDHTte+XlrDq1hy/Et9KjSgxalFKgzm9sWyFuWFQi0A364zMOrgWK2bVcFhgIT/uV9BliWFWdZVtyxy7W0FRER91q92oSrceOgcGEzwiVeZ8QIsxD+f/8zDf6vZO3htTT/tjnPzHmGpLSkrCswG3PnbsRWwGrbto/8/QHbts/Ytp1w4etfgQDLsi7b99+27eG2bcfath2bL5861oqIZBrbhqFDoV49SEoyB0k/8wxYltOVyTVIT4fHHzejWQ0bmtGtwMDLP3f9kfU0H9mcsIAwZt85m+AcwVlaa3blzrDVgytMIVqWVdCyzL9ey7JqX7juCTdeW0RErtX+/ab5UosWsHat+U0tXsXlgs6dzWjWoEEwdSrkynX55/525DeajWxGSEAIc3vPpUSuEllbbDbmljVblmWFAi2Ae/5030AA27Y/A24D7rUsKw1IBLrbtsapRUQcsXUrlC0L0dGwYgVUqKDRLC/l5we1a5u8/G8L4QGm7phKoH8gc3vPpVTuUllToABgeXLmiY2NtePi4pwuQ0TEN7hc5vDop582nS579XK6IrlOixebb+fVDEa6bBd+lpnIOnH+BHlC82RyddmXZVmrbNuO/fv96iAvIpIdHD0KrVvDE09Ap07mMGnxSiNGQNOmZp3Wf42XbD62mRs+vYG1h9cCKGg5RGFLRMTXLVhgusDPmweffQbffw85czpdlVyj9HSTlfv0Mf2zpkz599nfLce30GREE46fP66F8A5TS2AREV935owJV1OnQtWqTlcj1yExEbp3h0mTzJngH354+Y7wF207sY2mI5piYzOv9zzK5y2fdcXKP2hkS0TEFx08aEawANq0gfXrFbS8WFAQhIaaTh2ffPLvQWt3/G6ajGhCmiuNub3nUiFfhawrVC5LI1siIr5m+nSz+D0lBVq2NL0A/u23s3ispUuhYEEoUQLGjLm6TaMFwwvStERTnqj/BBXz6fBwT6CRLRERX5GaCk8+CbfcYn5DL1165aZL4vFGjYLGjeGhh8zt/wpau+N3cyrxFME5gvm247dUzl8502uUq6OwJSLiC9LTzVktb75pzjhcvtz0zxKv43KZ7hy9esGNN8KXX/73a3ad2sVNX99E9x+7Z36Bcs00jSgi4gv8/aFDBxgyBLp2dboauU7nzkHPnjBhAvTvDx99dOWjdy66uEYrISWBN5u/mSV1yrVR2BIR8VbJyfDYY9Cqlfl4+GGnK5IMsm3Ytw/efx/uv/+/pw73xO+hyYgmnE4+zew7Z1OtYLWsKFOukcKWiIg32rEDunWD1ashTx4TtsRrrVoF5cpBeLhZane1+xn6TepHfFI8s3rNokahGplbpFw3rdkSEfE2Y8dCjRqwaxdMnAgvvOB0RZIBo0ZB/fpmbwNc28bRr9p9xaxes6hZuGbmFCduobAlIuJN5s6F22+HKlVg7Vodu+PFEhPNXoZevaBuXXjppat73YEzB3huznO4bBfFooopaHkBhS0REW+QmGg+N25shkLmzYOYGCcrkgzYvh1q14bhw80RPDNnmtng/3Lw7EGajGjCB8s/YMfJHZlfqLiFwpaIiCezbfjqK9PVcscOs2L6jjvUpNTLhYSYbh3TpsEbb1zdt/PQ2UM0HdGUQwmHmNZzGmXzlM38QsUtFLZERDzV2bNmjumuu6BiRQgLc7oiyYCzZ+Htt00fraJFYcMGuPnmq3vt4YTDNB3ZlP1n9jP1jqncGH1j5hYrbqWwJSLiidasgZo1zWL4//s/M89UqJDTVcl1WrvWfDufeMLsNgTwu4bfwFuPb+X4+eNMvWMqDWIaZEqNknnU+kFExBN9/rnpcDlnDjRq5HQ1cp1s2xwc/fDDkDev+XbWr3/1r09JTyHQP5BGxRux64FdhAeGZ16xkmk0siUi4ini42HbNvP122+b4RAFLa92332mqX/z5tf+7Tx27hixw2P5es3XAApaXkwjWyIinmD5cuje3azLWr8eQkPNh3i17t2heHEzsnUt04bHzx+n2chmbD+5nWJRxTKtPskaGtkSEXGSy2VGsRpcWIfz5ZfX9ltZPIrLBW+9Bc88Y243aACPPnpt39IT50/8EbQm95hM0xJNM6dYyTL6Fy0i4pTTp6FtW3O+Yfv2ZlF8nTpOVyXX6ehRaN3aLILfscMEr2uVlJZE82+bs/X4ViZ2n0jzks3dX6hkOU0jiog4JTTUNCv9+GO4997/PnVYPNbcuab92cmT8OmnpjP89Xw7g3ME071Sd6oVrEbLUi3dX6g4wrJt2+karig2NtaOi4tzugwREfdJT4cPPoA77zTb01wuTRt6uePHoVgxiI6G77+HqlWv/T3ik+LZE7+HqgWv48XiMSzLWmXbduzf79fIlohIVjl0CHr2NPv//fzgwQcVtLxYfDxERZnMPGmSmQEOv44Ng/FJ8bT8tiV7Tu9h5/07CQtU81pfo3/lIiJZYeZMqFbNdLT86it44AGnK5IMmDoVypQxPWcBmjW7vqB14vwJbh51M2sPr+WLtl8oaPkohS0Rkcz27bfmXJZ8+SAuDvr21fosL5WSYvYztG4NhQtDjRrX/177Tu+j4dcNWXd4HeO7jqdtubbuK1Q8isKWiEhmu/lm02hpxQpzxqF4pV27oGFD06lj0CDTGq1cuet/vzcXv8mBsweY3nM67cq1c1+h4nEUtkREMsOkSaadQ1oa5M9vfkOrSalXW7kStm6F8ePNBtLg4Ot7n4sb095p+Q7L7lpGo+I6JcDXKWyJiLhTcrJZ+N6+PezfDydOOF2RZEBSEsyfb77u2hV+/x06d77+95v5+0zqfVmPk4knCcoRRIV8FdxTqHg0hS0REXf5/XdzyvAHH8D998OSJVCggNNVyXXassXsMLzlFrORFCBPnut/v+83fM+tY24lMS2RlPQU9xQpXkFhS0TEHWz70tDHzz+bwBUU5HRVcp1GjoTYWDh4EH78EQoVytj7fbziY3r82IO6Resyv898CoYXdE+h4hXUZ0tEJCMSE83OwuBg+OYbiIw0HS7FK9k29OtnvpWNGsHo0VCkSMbe87O4zxgydQjtyrXju87fERIQ4pZaxXtoZEtE5Hpt3mzmmR55xNyuUkVBy8tZlmnp8MILMHt2xoMWQLty7Xiy/pP82PVHBa1sSmFLROR6jBhh5pkOHTKHSYvXsm347DNYsMDcfvVVePFF8Pe//vdMTkvmvaXvkeZKo3BEYV5v/jo5/DSZlF0pbImIXIuEBHOuYZ8+ULs2rFtnVlCLV4qPN0vt7r3XTB26w9nks7QZ24aHZzzM7J2z3fOm4tUUtkRErsXBgzBxohn6mDXLzDmJV1qxAqpXN/sZ3nwTvvgi4+957Nwxmo5sytxdc/mm/TfcXPrmjL+peD2NaYqI/BfbNmcbtmgBZcvCzp0Z6wEgjlu50nTpKFwYFi6EevUy/p574vdw86ib2XN6DxO6T6BN2TYZf1PxCRrZEhH5N6dPQ7du5sidKVPMfQpaXutC83Zq1oSXXoK1a90TtACOnDvCudRzzOw1U0FL/kJhS0TkSlauNPNMP/1k5plat3a6IsmA+fOhalXYtw/8/ODppyFXroy/74EzBwCoXaQ2O+7bQYOYBhl/U/EpClsiIpczfLiZZ0pPN/NMjz9ufkOL10lPh//7P2ja1By/c+aM+9576vaplP2oLCPXjQQgKIca2co/6SeHiMjlFC4Mbdq4d55JstzBg2ap3QsvQI8esGoVVKrknvcevX407b5rR7k85biltHakypUpbImIXLRoEQwbZr5u08ZMH7pjnkkc8/LLsHw5fPUVfPstRES4530/WPYBPX/uScOYhszrM4/8Yfnd88bikxS2RERcLnjtNWjcGN5/H5KTna5IMiA19dLB0W++CXFx0Lev6Q7vDmsOreHB6Q/SqUInfr3jVyKDIt3zxuKz1PpBRLK3I0egVy/T2qFHD9NKXAdIe63du8238fx5E7IiI82HO1UvVJ3pPafTrEQz/P0y0GZesg2NbIlI9nXunOkBsGiR6Wg5erT7fzNLlvn5Z7N5dNMmeOYZCAhw33snpSVxx093MH/3fABalmqpoCVXTWFLRLKfi82WwsJMJ/gVK+Cuu9w3zyRZKjkZ7rsPOnWC0qVhzRpzBI+7nEk+Q6vRrRjz2xg2H9/svjeWbENhS0Syl/37zdqsadPM7bvvhsqVHS1JMsa2zeDkQw/B4sVQsqT73vtIwhEaf9OYRXsXMbrTaAbGDnTfm0u2oTVbIpJ9/PKLOUA6ORnOnnW6Gsmg8eNNW4ecOWHJEggJce/7Hz13lAZfN+Dg2YNM7jFZ7R3kumlkS0R8X0oKPPIItG0L0dGm2VKXLk5XJdfp3Dno1898Cz/4wNzn7qAFkDc0Ly1KtmBWr1kKWpIhGtkSEd/388/w7rsweDC8/TYEBztdkVynDRvMeqwtW+DZZ82RO+62ZN8SikQUoVhUMT659RP3X0CyHYUtEfFdBw5AkSLmt3N0NNx4o9MVSQZMnmy+lTlzmk4dzZplwjW2Tqbr+K60LNWSid0nuv8Cki1pGlFEfM/583DPPVChAuzaZXYZKmh5verVoX17WLcuc4LWiLUj6Ph9R6rkr8KX7b50/wUk21LYEhHfsmED1K5tDpIePBiKFnW6IsmAuDiTm10u86387jsoUMD913l7ydv0mdiHJiWaMPvO2eQNzev+i0i2pbAlIr5j+HCoVQuOHYPp0+H1193b2VKyjG2bk5NuvBGmTjUdOzJLUloSY34bQ9dKXfmlxy9EBLnpAEWRC7RmS0R8R1wcNGwII0dCwYJOVyPX6cQJs9tw0iRo1w6+/hpy53b/ddJcaaSmpxISEMKc3nOICIxQV3jJFApbIuLdli0z+/6rVoWhQ81Ilp8G7b2VbZuAFRdn2jrcd1/mNPZPTE2k6/iuuGwXk3tMJio4yv0XEblAP5FExDu5XPDmm9CgATzxhLkvKEhBy0ulp0NqqglW77xjmpTef3/mBK34pHhajmrJlG1TaF26NX6W/puRzKWRLRHxPkeOQK9eZv9/ly5mrZZ4rcOHzbezRg2Tn+vWzbxrHTp7iJtH3cyW41sY23ks3Sp3y7yLiVygsCUi3mXLFnO24enTJmTdfbcOkPZiM2dCz57m9KTu3TP3WrZt0/H7juw8tZMpt0+hRakWmXtBkQsUtkTEu5QqBa1awaOPQqVKTlcj1yktDZ5/Ht54w7RDmz07888DtyyLj1t/jMt2UatIrcy9mMifaKJaRDzfrl3QqRMcP24WwH/9tYKWl9u+3Zyg1K8frFyZuUFr3u55vDz/ZQBqFq6poCVZTmFLRDzbDz9AtWpm6GPTJqerkQxau9Z8rlABNm6EL76A0NDMu97Pm3/m5lE3893G70hISci8C4n8C4UtEfFMF4/c6drV/GZeuxZuusnpquQ6JSfDgw+aI3cmTzb3lSqVudf8YvUX3PbDbdQoVIMFfRYQHhieuRcUuQK3hC3LsnZblvWbZVlrLcuKu8zjlmVZH1qWtcOyrPWWZdVwx3VFxIc9/rhZAP/EE7BwIZQo4XRFcp127DCd4D/4wLRzaNky86/51uK36D+5Py1LtWRWr1nkCc2T+RcVuQJ3LpBvYtv28Ss81gooc+GjDvDphc8iIpfYNpw7B+HhZvV0+/bQQjvGvNn48WZdVo4c8PPP0KFD1ly3aGRRet7Qk6/afUWAv45sEmdl1TRie2CkbSwDoizLKpRF1xYRb3D6tNn736qV2aqWP7+Clg9IS4MqVcwscGYHrdT0VJbuWwrA7VVu59uO3ypoiUdwV9iygRmWZa2yLGvAZR4vAuz70+39F+4TETFH7lSrBj/9BG3bqgu8l9u0Cb7/3nzdvbuZBY6Jydxrnks5R/vv2tN4RGP2xO/J3IuJXCN3/USrb9t2Dcx04WDLsv6+ivVyHQfty72RZVkDLMuKsywr7tixY24qT0Q80sUjdxo2NLcXLjRrtRS2vJJtw1dfQWys+TYmJZn7M/vbeTLxJC2+bcH036cztNVQikUVy9wLilwjt/wTsG374IXPR4Gfgdp/e8p+IPpPt4sCB6/wXsNt2461bTs2X7587ihPRDzV+fPw+edmfmnNmsw9p0Uy1ZkzphP8XXeZxfDLl0NwcOZf98CZA9z09U2sOrSKcbeNY0DNy02uiDgrw2HLsqwwy7IiLn4NtAQ2/O1pk4A7L+xKrAuctm37UEavLSJeav58SEw0C+GXLoVx4yAqyumq5DqdPw+1asF338Err8D06VCwYNZce8S6Eew9vZdpd0yjc8XOWXNRkWvkjpGtAsAiy7LWASuAKbZtT7Msa6BlWQMvPOdXYCewA/gcGOSG64qIt0lNhSefNGcbvv22uS9fPp1t6KXsC4tBQkOhf3+YNw+eeQb8/TP/2mmuNACeavAUaweupUmJJpl/UZHrZNn2ZZdOeYTY2Fg7Lu4fbbtExBvt2gW3324Www8YAO+9l7mtwyVTrV9vAtZbb0GjRll77Vk7Z3HvlHuZ3nM6JXOVzNqLi/wLy7JW2bYd+/f7tQpVRDLfjBmmdfimTWbKcNgwBS0vlZwMzz0HNWua/JyQxSfgjNs4jtajWxOSI4TgHFmwKEzEDRS2RCTzFS9utqitXQtdujhdjVynJUtMh45XXoEePWDzZrj11qy7/qcrP6X7+O7ULlKb+X3mUziicNZdXCQDFLZEJHNs3GgW8Ng2lC0Ls2bpyB0vt3KlWQw/dSqMHAl5svAEnDG/jWHQr4O4teytzOg1g1whubLu4iIZpDVbIuJetm3aOTzwAERGwurVUEQ9jL3Vr79CSorpzpGefmkTaVZLSEngg2Uf8Hj9x9UVXjyW1myJSOaLj4du3eCee0yj0nXrFLS81LFjcMcdZprw/fdNhvb3z9qglZKewgtzX+Bs8lnCA8N55qZnFLTEKylsiYh72LY5y/Cnn+CNN2DatKxrtiRuY9swejRUqAA//AAvvGD6ZmV1d46ElATajGnD/y34P6bumJq1FxdxsxxOFyAiXs7lMp/9/ODVVyEiAurVc7YmuW6LF5tO8HXqwJdfQqVKWV/D8fPHaT26NasOreKrdl/RtVLXrC9CxI00siUi1+/IEWjV6lKD0pYtFbS8kMsFq1aZrxs0gEmTTOhyImjtPb2XBl81YP2R9fzc7Wf6Vu+b9UWIuJnClohcn5kzoWpVWLAAcud2uhq5Tlu2wE03Qf36sHu3ua9t26zpAn85aa40LMtiRq8ZtCvXzpkiRNxMYUtErs3FI3datoS8eU0/gLvvdroquUYpKaZfVtWqptfssGFQrJhz9Ww7sQ2X7aJkrpJsuHcDNxW7ybliRNxMYUtErs26dWbacMAAWLECKld2uiK5RikpULeu6QTfoYNpTtq7t3NHVE7bMY3qw6rz5qI3AfD3c2hYTSSTKGyJyNX57TfzOTYWNmzQkTteKDXVfA4MhK5dYeJE+P57KFDAuZrG/jaWtmPbUjZPWfpV7+dcISKZSGFLRP7d+fOmb9YNN5j1WQDlyztbk1yz2bNNO4f5883tJ5+Edg4vifpw+Yfc/tPt1I+uz7ze8ygQ7mDqE8lEClsicmUbN0Lt2jB8ODzxhHYaeqFTp6BfP2je3HTnCPCQnqC7Tu3isZmP0aF8B6b1nEbO4JxOlySSadRnS0Qu76uvYPBgc+TO9OlmQbx4lQkTYOBAOH7cjGQ9/zyEhDhbk23bWJZFiVwlWNh3ITUK1SCHn34ViW/TyJaIXF5S0qUjdxS0vNLevVC4sNkw+vrrzget5LRkuo3vxuj1owGoXaS2gpZkCwpbInLJ8uVm1TTAvffqyB0vY9vwxRcwbpy5PXiw2TBavbqzdQGcTT5L6zGt+WHTDxw/f9zpckSylMKWiJgW4m+9ZdqHP/+8uW1ZZpGPeIUdO6BZM+jf/1LY8veHHB4wcHT03FGajGjC/N3zGdlhJA/UfcDpkkSylH6SimR3F4/ceeIJ03Rp/nyFLC+Slgb/+x9UqWKO3Bk27FLY8gRnk8/S4KsGbDq2iYndJ9Krai+nSxLJch7w/zwi4phjx0wL8dOnzW/p/v2d62wp12XuXHj8cWjfHj7+GIoUcbqiv4oIiqBPtT40KtaI+jH1nS5HxBGWbdtO13BFsbGxdlxcnNNliPge274Uql591fymVid4r5GUBEuXQpMm5vbixXDjjZ6VkxfvXUxQjiBiC8c6XYpIlrEsa5Vt2//4j15zBSLZza5d5rf02rXm9jPPKGh5kYULzWBkq1Zw6JC5r359zwpav2z7hebfNufBaQ/iyf9DL5JVFLZEspMffjBb09asgQMHnK5GrsGZMzBoENx0kznbcPJkKFTI6ar+aeS6kXT4rgOV8lXip24/YXlSChRxiMKWSHaQmGi6W3btao7aWbsWbr3V6arkKp0/b05L+uwzeOghczRlixZOV/VP7yx5h94TetO4eGPm9p5L/rD8Tpck4hG0QF4kO/j0U7MA/okn4OWXPefMFvlX585BWJg57/vhh6FOHfPhiVy2i7m753JbxdsY1XEUQTmCnC5JxGNogbyIr7JtOHzYzDWlppqGpQ0aOF2VXAXbhlGjTMD64Qdo3Njpiq4szZXGmeQz5A7JTWJqIoH+gfj7+TtdlogjtEBeJDs5fRq6d4dateDkSTOSpaDlFfbsMYvf77wTypSBAgWcrujKziSfocN3HWg2shnJacmEBIQoaIlchsKWiK9ZvhyqVYMff4QhQyAqyumK5CoNHw6VKsGiRfDhh2bnYYUKTld1eTtO7qDuF3WZtmMa99S8R9OGIv9Ca7ZEfIXLBW+/bVo5FCliflPXq+d0VXINLp79/dlnUKyY09Vc2ayds+j6Q1csy2Jmr5k0KdHE6ZJEPJrWbIn4CpfL7DAMD4fPP9eIlhdISYE33oBSpeCOOy4dSenJ3RLSXenUHF6TdDudid0nUjJXSadLEvEYV1qzpZEtEW83axaUKwfR0WbqMCTEs39bC2Bme+++27RxGDTIhC1PPpIyJT2FdFc6IQEhTO4xmajgKCKCIpwuS8QrePA/bRH5V6mp8NRT0LIlvPiiuS80VEHLw507Z3pl1asH8fGmOenHHztd1b87eu4oTUc0pe/Evti2TXTOaAUtkWugsCXijXbvNq3E33jDDI8MHep0RXKV5s+H9983PWY3boQ2bZyu6N+tPbyW2OGxrD60mo7lO6ojvMh10DSiiLdZutT0BrBt+O476NbN6YrkP5w8aQ6LbtsWWrc2IatiRaer+m8/bPyBPhP7kDskNwv7LqRm4ZpOlyTilTSyJeJtKlWCW24x5xsqaHk024Zx40z7hh49TOgC7whap5NOc++Ue6lWsBor+69U0BLJAIUtEW+wcaP5bZ2UBJGRZkSrpHaBebIDB6BDB5OHo6PNyFbu3E5X9d/Op57Htm1yBudkbu+5zLlzDgXDCzpdlohXU9gS8WS2bdo41KoFc+bA9u1OVyRX4fRpc3D0zJnwv//BsmVQtarTVf233fG7qfdlPV5f9DoAVQpUUbNSETfQmi0RTxUfD/fcY+ahmjeHb7+Fghph8GTHjkG+fJAzJ7z1ljnTsFQpp6u6Ogv2LKDzuM6kudKILfyPNkEikgEa2RLxVH37mr5Zr70G06craHmwtDR4803T9X3uXHPfXXd5T9Aavmo4zUY2I09IHpbfvZyWpVo6XZKIT9HIlognSU+H5GTTL+uNN+CJJ6BuXaerkn+xZo0JVmvWQKdOUL680xVdm20ntjFoyiBalmrJ2M5jyRmc0+mSRHyOwpaIp9i/H3r1ggIFYOxY0xVePNrLL8NLL5mpw/HjoXNnpyu6eslpyQTlCKJsnrLM7zOfukXr4u/n73RZIj5J04ginmDiRLOCeuVK00NLvELu3NC7N2za5F1Ba8PRDVT6pBITt0wEoH5MfQUtkUyksCXipMREGDzY9AgoXhxWrza/vdWl2yOdPm06v48caW4PHgxffgm5cjlb17WYtHUS9b6sx/nU82rpIJJFFLZEnHTqlNlt+MgjsGQJlC3rdEVyBZMmmWakn39uTkvyNrZt89rC1+jwXQfK5y3Pyv4rqVO0jtNliWQLWrMlktVs2/zmbtsWCheGrVu9o9tlNnXkCNx/v8nEVarAhAmm7Zm3mbZjGs/MeYbbq9zOF22/ICQgxOmSRLINjWyJZKWTJ+G228y04bhx5j4FLY+2cqUJWC+/DHFx3he00lxpANxS+ham3jGVUR1HKWiJZDGFLZGssnAhVKsGkyfD229D165OVyRXsHu3OREJoE0b2LkTnn0WAgMdLeuaLd23lAofV2DD0Q1YlsUtpW/B0npAkSynsCWSFYYONe3Eg4LM2qxHHgE//fPzNOnp8P775qzvIUMgIcHcX6SIo2Vdl2/WfkPjEY2xbRs/S/+tiThJ/wJFskK1aqaH1urVEKujUDzRhg1Qvz489JDJxatXQ3i401VduzRXGg9Pf5i+E/vSMKYhK/qvoGK+ik6XJZKtaYG8SGb56SfYuBGeew4aNjQf4pGOHoXatSEsDEaPhh49vLf7xicrP+G9Ze9xX+37eKflOwT4Bzhdkki2p7Al4m7nz8PDD8OwYVCnjjlyx9sW+2QTO3dCyZKQPz98/TU0bWq6wXsjl+3Cz/JjYOxAoiOj6Viho9MlicgFmkYUcaf16812tWHDTMhasEBBywMlJMADD0CZMpcOju7WzXuD1rQd06j1eS1OnD9BoH+ggpaIh1HYEnGXM2egUSPT3mHmTHOQtIKWx5k+HSpXNnsW7r3Xu5fQ2bbNO0ve4dYxt5LuSud86nmnSxKRy9A0okhGJSSYldSRkTBqlFn8461DJD5u8GD45BMoX9504qhf3+mKrl9SWhIDfxnIiHUj6FyhMyM6jCAsMMzpskTkMjSyJZIRc+dCuXIwdqy5feutCloexrbNB8ANN5h+WWvWeHfQAnh85uOMWDeCFxu9yLgu4xS0RDyYRrZErkdqKrz4Irz+ujnPsHx5pyuSy9i61bQ069LFnO99zz1OV5Rxtm1jWRbP3vQszUs2p125dk6XJCL/QSNbItdq1y646SZ47TXo1w9WrYLq1Z2uSv7k6FEzZVipEsyfD0lJTlfkHmN/G0vbsW1JTU8lf1h+BS0RL6GwJXKtVq6EzZvNeS5ffGGaM4nH+OorKF3abAgdMAB27PD+ES2X7eLp2U9z+0+3cyb5DAkpCU6XJCLXQNOIIlfj3DlYtgyaNTNnGjZrBnnyOF2VXJCebmZ2g4PNkrmmTc1mUF+Y3T2TfIaeP/Vk8rbJ9K/Rn49af0Sgv3a5ingTjWyJ/Jc1a6BmTWjb1sxPgYKWh7BtmDbNzOK++qq5r21bmDDBN4IWQPfx3fl1+6981OojhrUZpqAl4oUUtkSuxLbNqcR168LZszBlimk1Lh5h7Vpo2RJatTIDj766bO61Zq8xo9cMBtcejOWtZwiJZHOaRhS5nPR06NABfvkF2rWDL7+EvHmdrkoueO89s8swVy7z9b33QlCQ01W5h23bfLLyE3ac3MF7t7xHtYLVnC5JxGO40l2kJKSQcjaF5DPJJJ9NpmidogDsXbSXQ6sPkXw2meQzyaScTcGV5qLt8LYOV+2GsGVZVjQwEigIuIDhtm1/8LfnNAYmArsu3PWTbdv/l9Fri2Qaf3+oUQNuuQUGDfLeU4l9yOnTkJxsBhebNoVHH4Wnn4aoKKcrc5+U9BTu+/U+hq8eTtuyZtehDpIWX5GSkMLZg2dNSLr4cTaZ8h3KExQRxK45u9j882ZSzlwKUslnkuk1sxfBOYOZ89wcFr6y8B/v+0zSM+QIysHGcRtZMXQFAP5B/gRFBhEcFfxHuxQnuWNkKw14xLbt1ZZlRQCrLMuaadv2pr89b6Ft223ccD2RzJGSAs8/b+alGjWCl15yuiLBfFs+/RReftl8a779FqpWNR++5Ni5Y3Qe15mFexfydIOnebnpy/hZWukhzrBtm7SkNJLPJBMUEURAaADnjp1j/7L9l0aVLnxU61uN3KVys3v+bha+uvCvj59Npvfc3hSqXoj1o9czZeCUf1xr0KZB5KuQj6MbjrJhzAYCIwIJigwiKCKI0DyhuFJdABRvVBw/f79Lj1/4sPxMkGr8UmMavdCIoIgg/AP9s/Kv6z9lOGzZtn0IOHTh67OWZW0GigB/D1sinuv336FHD9PWISDAhC1xlG3D+PHw1FPm29OsGTz8sNNVZY50VzqNRzRm56mdjOk0hh5Vejhdknip9JT0v4wKpZxNIWdMTnLG5OT8ifOs/WbtH/df/FxjQA1KNivJoTWH+L7j93+ZggPo8kMXKt5WkcNrDvNdu+/+ekELYhrGkLtUbux0m5SzKQRGBBJRJIKgyCACIwIJjgoGoETTEnQa3ekvYSooMoicMTkBqHN/HercX+eKf7aSzUtSsnnJKz4ekiskg397mceta7YsyyoOVAeWX+bhepZlrQMOAo/atr3RndcWuW6jRplFPzlymN/unTs7XZFgWjc8/bQ5NPrXX82Mrq/O5vr7+fN6s9cpHFGY2MJefDK2ZIht2xzdcPQv65GSzySTt1xeYhrEkJaUxtQHpppptj+FqWr9qlHnvjqcPXiWd4u8+4/3bf5Wc+o/Vp+kU0nMfHQmgAk8F8JO4olEwISV4o2KExh56bHAiEAKVisIQJE6Rei/sv8f9wdFmhGvi1N0JZqW4K6ld13xz5enTB7ylMmeO7kt++KhYRl9I8sKB+YDr9q2/dPfHosEXLZtJ1iW1Rr4wLbtMld4nwHAAICYmJiae/bscUt9Ipf166/mPMMGDWD0aIiJcbqibG3bNtMvq1IlOHzYbADt08csofM1LtvFy/NfpnBEYfrX7O90OZJFfp/5Oye2nuDE9hOc2nGKE9tPULJ5SW795FYAXgl+hfTk9L+8pubAmrT5tA2udBfvFnn3L6NCQZFBVOxakRvuuIG0pDSWvLPkH4/nKZeHnNE5caW7SD2XSmB44B9Tb+JelmWtsm37H//H5JawZVlWAPALMN227X/G6n8+fzcQa9v28X97XmxsrB0XF5fh+kT+4dw50/nd5TIjW7ffbka2xBFHj5olcsOGQfPmpneWLzuXco7eE3rz4+Yf6V+jP8PbDne6JHGT+D3xHN9ynJPbT3Jyx0lObj9JeOFw2n1ujlb6sPSHnPr9FAFhAeQpk4fcpXNT6uZS1Li7BgBbJm4hR3COvwSmkNwhBIarv5o3uFLYcsduRAv4Eth8paBlWVZB4Iht27ZlWbUx/b1OZPTaItfM5YJ334W33zbrs6Kj4c47na4q2zp/3rRuePNN8/WAAfDCC05Xlbn2xO+h/Xft+e3ob7zT8h0eqvuQ0yXJNXCluYjfE/9HkDq54yRpyWm0+dTs/5rYZyK75+0G+CNQ5Sqd64/Xd5/QndC8oYQVCLvsDrny7X2kG6/8hTv+V74+0Av4zbKstRfuexqIAbBt+zPgNuBey7LSgESgu+2u+UuRq3X4MPTuDTNmQKdOOtPQAwwbBs8+a1qavfEGlCvndEWZ61TiKWp/UZvktGSm3D6FW0rf4nRJchmuNBen957mxPYTnNx+kvg98bR4qwWWZTHprkmsG7nuj+cGhAVQoEqBP9oLNHmlCbbLJk+ZPJcNVPkrqzFyduS2NVuZQdOI4jbTppmgdeaM6Qo/YIDvrrb2YLZtsq5tmwXviYmwejXUr+90ZVnn4xUf07xkc8rl9fFk6eH+Eqh2nKRa72oEhgey5J0lzH5q9h/tBsAEqof2PURIrhB2zdlF/O54cpfJTe7SuQkvGO54DyfxHJk2jSjiFUaNMt0w58wxq68ly61dC489BrNmmXVZt9wCISG+H7RS01N5bOZjdK7QmYbFGjK49mCnS8o2/hyoCtcsTGjeULZN2caMh2dwatepvwSqonWLUrhmYQrVKES9R+qRu3Rus6aqzF8DVYmmJZz644gXU9gS37Vtm/lctqzpipkjh/ntLllq3z4zVfjtt+Z4nfffN502soMT50/QdXxX5uyaQ+6Q3DQs1tDpknyOK93F6T2nCYoMIjRvKMc2HWPm4zM5uf3kXwJVtwndKN++PKF5QslfJT/lO5X/R6ACKNGkBCWaKFCJeylsie+xbRgxAoYMgTp1YPZsiIhwuqpsa/Fi+P57M6r11FO+dbzOv9l0bBPtxrZj35l9fN3+a/pU6+N0SV7Lle4iLSmNwLBAEk8mMv/l+X8sTj+10wSqVkNbUXtIbfwC/Diz74wJVB3L/zHdd7FXVNG6Rek6vqvDfyLJbrRmS3zL6dNm2GTsWNMFftQoKFrU6aqylZQU+Owz0xtr8GCTfQ8ehCJFnK4s62w+tpk6X9QhNCCUn7v9TL3oek6X5DVc6S5WDVv1x26/E9tPcGrnKeo+VJcWb7Yg+Wwy7xR8h9ylTYjKXcZ8FLupWLZtmCmeQ2u2xPft2AEtW8LeveYgvaee8s1umB7KtuHHH81f+44d0LGjCVuWlb2CFkC5vOUYUnsIg2oNomikwv7f7Z63m2Objv2lfULRukVp/3V7/Pz9mPPsHNKT08ldOjf5K+WnfIfyfxzTEhQRxFMJT2lRungVhS3xHdHRcMMNZjTrxhudriZbWbPGBKulS/96vE52kpiayKMzHuXx+o9TLKoYrzV7zemSHHNm/xmObf5TmNp+kuBcwXQc2RGAqfdP5ehvR8kRkoPcpXOTr2I+CsUW+uP1Q7YOITRv6BUDlYKWeBuFLfFuBw+aA/Q++ABy5oQJE5yuKFuxbTNylZQEe/bAF1/47vE6/+bAmQO0/649qw+tJrZwLH2r93W6pExn2zandp5i3+J9HF57mKTTSbT/sj0Av9zzC9t/3Q7wR6AqWujSCF/nsZ0JjgomonDEZYNTWD71wBPforAl3uuXX6BvX9N6vHdvaNLE6YqyjWPHzPE6lgVDh0K9erBrFwRmwxNFlu9fTofvO5CQksCE7hNoV66d0yVlivTUdPxy+GFZFsuHLmfRa4tIOJwAmECVt1xeXOku/Pz9uOm5m7jx8RvJXTr3ZQNV/kpq7CnZi8KWeJ+kJHjiCfjwQ6hWzSyGL68jLrLC+fOmdcMbb5ivBw26NLqVHYPWnF1zaD26NYUjCjOz10wq56/sdEluk3wmmf3L9rN30V72Ld7H/mX7Gbh+ILlL5SYsfxglm5ckun40MQ1iyFcx318ONi5aV+vURP5MYUu8z0MPme1uDz5ofusHBTldUbawYIE5r/vAAWjf3vzVZ/eMW7tIbfpW68srTV8hT6h374Q7ve80ASEBhOYNZcf0HYxpPQbbZWP5WRSsVpDqd1XHz98PgMrdKlO5m+8ES5HMptYP4h1s25ztEhoK+/fD+vXQurXTVWUL586ZYyT37DFndr/yCjTMxr0545PieXHei7za9FXCAr1zbZHtsjm64egfo1Z7F+3l9N7T3PzezdR9sC4JRxKI+zSOmAYxFKlThKAI/Q+NyNW4UusHhS3xfPHx5izD06dh6lTw83O6omxh7Vp4/HEzRTh9utPVeIZtJ7bRbmw7fj/1O1Nun0LLUi2dLumqpJ5P5cDKAwAUb1SclIQU3oh6AzvdJrxQODENYohpEEPpVqXVq0okA9RnS7zTkiWX5q5eecXparKFvXvhuecuHa/z/PPgcinjTt8xnW7juxHgH8DsO2dzU7GbnC7pX23/dTs7Z+9k3+J9HFp1CFeai+JNilN8TnECwwPpPqE7+SrlI6p4lFopiGQyhS3xTOnp8NprZstbsWLmzJfatZ2uyufNmAHtLmymy27H6/ybUetH0XtCbyrnr8zE7hMpHlXc6ZL+YNs2J7aeYO/ivcTvjqfpy00BWPb+MvYs2EORWkWo92g9YhrEEF0v+o/XlW1T1qmSRbIdhS3xTGfPwvDh0K2bOUQ6MtLpinxWSopZBleyJNSta7ppPPmkybhi1I+uT5+qffig1QeEB4Y7XQ4A237ZxuovVrNv8T7OHz8PQFj+MG569iZyBOWg/dftCc0bSo4g/ZgXcZrWbIlnmTULbrrJ9BE4ehTy5TOLhsTt/ny8To4c8Ntv5rMYhxMOMyxuGM83et7RabbEU4nsX3qpBUPHUR3JGZ2TFR+vYPkHy4mpH0N0g2hi6seQp1weTQmKOEhrtsSzJSbCI4+YUaz33jNtHfKr8WFmWbzYTBNePF7nrbeyX9f3f7P60Graf9eek4kn6VKpCxXzVcyS69q2jZ1u45fDjwMrDjDprkkc3XAUAL8cfhSqUYjzx8+TMzontQbVovZgTa2LeAOFLXHexo3QvTts2GAC16BBTlfk02bONOd1FyqUfY/X+Tffb/ievhP7ki8sH4v7Lc7UoOVKc3Fk/ZG/tGBo8HQDag+uTXjBcCKKRFCpWyXTgqF2EQJCA/54rUawRLyHwpY4a9w4c9ROZCRMmwY33+x0RT7p6FHYtAkaN4amTc0RO337mv5Zcsmbi97kydlP0iCmAT92/ZH8Ye4dXU0+m0ziiUSiikeRmpjKOwXfIflMMgA5Y3JSrFEx8pTN88ftntN6uvX6IuIMhS1xVvnyJmANGwYFCjhdjc85f97Myr75pukHu3evWQ43ZIjTlXmmOkXrcE/Ne/iw1YcE+mf8/KGzB8+yd9Fe9i7ey75F5sDmks1L0nN6TwJCArjxMXN+YHT9aHJG53TDn0BEPJEWyEvWmz/fdMl87TWnK/FZ6ekwcqTpl6Xjdf7dzlM7mb1zNv1r9s/Q+9gum2Obj3F883Eq3mamHkc0GcHuebsJCA2gSJ0ixDSIoXiT4pRoUsIdpYuIh9ECeXFeWhq8/LJpTlqypGlPriZOmWLpUujXz7QmGzPGbPCUf5q7ay63/XAbFhadK3Ymd0jua3r90Y1H2TppK/sW72Pfkn0knUrC8rd4Mv5JAsMDafpqU/wC/ChYrSD+AVoYJ5JdKWxJ1tizB+64w2yD693bLBqKiHC6Kp+ybh2sXAl33w0NGsCcOWaNltZRX94nKz/h/qn3UzZPWSb1mPSfQevcsXPsW2IWsd/46I2EFwjn9xm/M+fpOeQtn5cKnSuYY2/qxxAQZhayR98Y/a/vKSLZg8KWZL7UVGjUCE6ehFGjTOgSt9m3D5591hyvU6CA+esNCYEmTZyuzHPd9+t9fLTyI24tcytjOo8hMujyTXNP7jjJojcWsXfRXk5sPQGAf6A/ZVqVIbxAONX6VKNqr6qE5g3NyvJFxMsobEnmSUyE4GAICDAL4EuXhlKlnK7KZ5w+bdZhvf++aVD66KOmQWlIiNOVeb6K+SryRP0neLXpq/j7+ZOeks6hNYf+aL9QsUtFqvSoAsCWn7cQfWM01fpWI6Z+DIVjC5Mj2PzoDMmlv2wR+W9aIC+ZY9066NEDBg82H+J2W7dClSrQtSu8+qqO1/kv64+s58CZA7Qq0wpXugs/fz/SU9IZdcso9i/bT1piGgC5SuWi/hP1qdm/JrZtgw2Wn+ZiReS/aYG8ZA3bho8+Mu3Jc+WCcuWcrshnXDxeZ/Fi086hXDnYtQuKFHG6Ms/3/ezveXv425Q9VJbdp3eTq3guuk/sjn+gP6F5Q6k5oKY5qLl+NBGFLq0ltCwLlLNEJIMUtsR9jh83W+AmT4bWreGbb8zZhpJhS5aYacKlS6FSJXNOd0SEgtaV2LaNZVm4bBcvN3gZlkAb2hAQHkB4vXCKNb40DNhlXBcHKxWR7EBhS9xn3TpzFsz778P992sbnBscPmxmYX/6yRyv8/nn5ngdHRj9T+mp6eyeu5vNP21m58yd9FvTj44TO3KwyEGa3N2ExwY8RnT1aPxy+DldqohkM/qRLRmTmgoLFkCzZuZj1y4oWNDpqryabUN8vJmFDQ42o1n/93/w8MM6Xudyjm06xuI3F7N10laS4pMICAug7K1lcZ11USlfJbo92Y27qt+lswRFxDEKW3L9du2C22+HFStg82YoW1ZBKwPS02HCBHj7bbORc80a0/N11y4ICnK6Os+RfDaZ7b9uJ3fp3BSuWZi05DS2Tt5KufblKN2+NN/k+IZSsaWILBTJ+0Xed7pcERGFLblOo0fDvfeCn59pUV62rNMVea3z583ytnffhd9/N831H37YhK8cORS0ABJPJbJ10la2/LSFHdN3kJ6cTq0htShcszAFqxXk0SOPsuP0Dnr82IM1h9eQL1c+qheq7nTZIiKAwpZcK9s2Lcq/+grq1zehSz0HMmT8eLMuq3Zt0zerY0fw18kupCamEhASgG3bDKs+jNN7ThMZHUnswFgqdKpAdP1L3dlHbhjJkKlDCMkRwqTuk2hbrq2DlYuI/JXCllwbyzLb4V56CZ5+Wiu1r8P27WYUq3JlE7K6dTOjWfXra0/B6b2n2fzTZjb/tJn4XfE8uOdBLD+LWz64hYjCERSOLfyPtVffbfiOfpP60aR4E77t+C1FIrVFU0Q8i35Tyn9LT4fXXzfpoEMHM8cl12zJErMea8IE01T/8cfN/UFB5izD7Gz71O3Me34eB+MOApC/Sn6q31WdtKQ0AkIDKN++/D9ek5iaSEhACLdVvI3zqefpU60P/n4aEhQRz6OwJf9u717o2RMWLjTDMB06OF2RV3rgAfjwQ7PD8OmnYciQ7LuXwLZtjm44yuYfN1OxS0XyV8r/R/PQZq83o0KnCuQpm+eKr093pfPW4rcYvno4cf3jyBOah7tq3JWFfwIRkWujsCVX9sMPMGAApKXByJEmdMlVSUw0f2Xt2pn+WB06mGMh+/WD8HCnq8t6tm1zcOVBM0X442ZO7jgJFkQUjiB/pfyUvqU0pW8p/Z/vc/DsQXr93Is5u+bQrVI3cvjpR5iIeD79pJLLW7zYHLpXu7bZbagDpK/K8ePw8cfmxKLjxyEpyYxqNWliPrITV7qLhMMJRBaJJC0xjRFNRpCekk6JpiWo92g9yncoT3iBq0+ev2z7hT4T+pCYlshX7b6iT7U+6p0lIl5BYUv+6vRpyJkTbrwRxo6Fzp3NAiP5V7ZtQtUXX5hRrTZtzPE6N93kdGVZ62IX900/bmLrhK1EFI7gnjX3EBAaQI9felCwakFCcodc8/vats0nKz8hOmc033X+jnJ5deamiHgPhS0xXC545x147TXTsrx8eeje3emqPN6WLeavyrJM1/cePeCRR6BiRacry3rL3l/G/JfmkxSfRGB4IGVuLUOFThX+OKewRJMS1/yeW45vISwgjOic0YzuNJrQgFCCcqjxmIh4F4UtgYMH4c47YfZs6NQJ8ud3uiKP5nLBL7/A//4HixbBxo0mXI0YkX1aNySfTWbH1B1s/nEzLd9tSWSRSMILhVOufTkqdKpAqZalyBF8/T9ebNvmqzVfcf+0+2lZqiU/d/uZXCG53PgnEBHJOgpb2d2kSWbVdmKiOeX4rruyT2K4RklJ8O23ZgBw61bTy/X99yEmxjzu639tKQkpbPpx01+6uIflD+PEthNEFomkcrfKVO5WOcPXiU+K555f7mHcxnE0K9GMT1p/4obqRUSco7CV3c2ebdLCmDFmPkz+wbZNkDp3Dh580Pw1jR0Lt93m+z1dEw4nkHgqkXwV8pF8NpmJfScSWfRCF/fOFYi+MRo/fz+3XW/TsU20Ht2aA2cP8EazN3is/mP4We57fxERJ/j4rwq5rPXrITUVataEN980SUIH8P3Dzp3w3nuwYQPMmQN58sC6dWZjpi+PYv3Rxf3HzexdvJfSN5fmjql3EFEogkEbBpG3Qt5M2wUYHRlNubzl+P6276lTtE6mXENEJKvpfxmzE9s2nTVr1zZb52wbgoMVtP5mxQrT9aJMGRg2DIoXN1OIAKVL+3bQmth3Iu8Xe5/pD00n6XQSjV5oRIv/tfjj8XwV87k9aB04c4CBvwwkMTWRiKAIpvecrqAlIj5FI1vZxdGj0Lcv/Pqr6Uvw1Ve+nRqu088/mz0COXPCY4/BffdBER88as+2bY7+dpTNP21m+5Tt9J7bm8DwQIo3LU6e8nlMF/cyV+7i7i4Tt0yk36R+JKcl07tqb+pF18v0a4qIZDWFrexg+3Zo2ND0JvjoIxg0SEHrgqQkGD3adHXv1g1uuQU++AD69IHISKerc7/4PfGs/GQlW37a8kcX95gGMSQcTiB36dxU7VU1S+pITE3ksZmP8fHKj6lRqAZjO4+lbJ6yWXJtEZGsprCVHZQsCe3bm2GayhnfLeYLTp6ETz+FoUPhyBHo2NGErZAQuP9+p6tzH1e6i32L9xGcK5gCVQqQFJ/EsneXXXcXd3fpP7k/o38bzSP1HuHVpq+qd5aI+DTLtm2na7ii2NhYOy4uzukyvNOmTfDQQ+aAvgIFnK7Go3z0ETzxBJw/DzffbKYLmzb1ncG+v3dxP3f0HNX6VqP9V+2xbZuk+CRCcl17F/eMsm2blPQUgnIEsfX4Vnae2kmrMq2yvA4RkcxiWdYq27Zj/36/RrZ8jW2bVd0PPWTmxnbuVNgCVq0yHS7y5TP9sW67zXR6v+EGpytzD9tlY/mZtDi85nCO/nb0L13cy7QuA4BlWY4ErVOJp+g/uT85/HIwtvNYyuUtpyN3RCTbUNjyJcePw913w8SJ0LKlaWlesKDTVTnG5YJp00yn93nz4MUX4YUXoG1b8+Htks8ms/3X7Wz5aQuHVh9i8JbB+Pn7Uf+J+gRFBlGqRca6uLvLor2LuP3H2zmUcIjXm73udDkiIlnO+Z/E4j5PP212G777rmnt4Jd9O3uMGAFvvWVmU4sWhbffhv79na7KPfYt3cfiNxb/pYt7+Y7lSUlIIThnMDfc4RnDdemudF5d+CovzX+JElElWNJvCbWK1HK6LBGRLKew5e1SUuDUKTNV+PrrcO+9UL2601U54vx5CA01X0+YAAEB5nidbt3M194q4XACWyZsoVijYqaT+5lkDq89TOy9sVTo5P4u7u5y7PwxPlz+IXdUuYOPW39MRFCE0yWJiDhCC+S92bZtcPvt5syYJUuy7UjWnj3mjMKvvoKVK6FsWThzBiIivHfRuyvNxdZJW1n5yUp2zdkFNjR7vRkNnmyA7bLBItO6uGfU/N3zaVisIX6WHwfOHKBIpA82KhMRuQwtkPcltg3ffGNaOQQFwRdfZMugtXq1mR4cN86Equ7dL51V6M09slzpLj6u+DEnt58kZ0xObnruJireVpH8lfMD/LEQ3tMkpibyyIxH+DTuU75s9yX9qvdT0BIRQWHL+5w+DQMGmITRuLGZJyta1Omqslx8PNSvb8LVAw+YA6Kjo52u6vrYts2uObv4ffrvtHirBX7+ftQeUpuoElGUaV3GI6cI/27D0Q10H9+djcc28mi9R+l5Q0+nSxIR8RgKW94mRw7YvNmsz3rsMfD3d7qiLJGSAmPHwoIF8OWXEBVl1mXVqWO+9kaJpxJZN2IdcZ/FcWLrCULyhFD3wbpEFI6gzv3eczbg6PWjuXvy3UQGRTLtjmncXPpmp0sSEfEoClveIC3NtDofMADCwkzTKG9e8X0N4uNh+HBzhM7Bg1ClitkPkCuXaUjqrfYu2su3Lb8lLTGNonWL0mFkByp1qeQRrRquVbGoYjQt0ZSv2n1FgXD1dBMR+Tvv+8me3ezaBXfcAUuXmoTRp0+2CVqLF0OrVnD2LDRrZhbAt2zpnYveUxNT2fj9RgLCAqjUpRKFahSier/qVL+rOoWqF3K6vGu2YM8Clu1fxuP1H6dBTAOm3D7F6ZJERDyWwpYnGzPGtHIAM4fWvbuz9WSBtWvNuYVNm0K1atC1qzk3u0YNpyu7Pid3nCTuszjWfLWGpFNJlGtXjkpdKhEQGkDrj1o7Xd41S3Ol8fL8l3ll4SuUzl2awbUGExYY5nRZIiIeTWHLU73+umlSWr8+jBoFxYs7XVGmsW2YOdN0ep81C2rWhLg4M2P6xRdOV3f9Zj01i8VvLMYvhx/lO5an1qBaFGtUzOmyrtue+D3c8dMdLN63mN5VezO01VAFLRGRq6Cw5Wls28yTdesG6enw5JOX+hn4oGnTzKHQ69dDoULwxhtwzz1OV3V9zh46y+ovVlPj7hpEFIqgWMNiBIQG/HHbmyWmJlLvy3okpCQwquMo7rjhDqdLEhHxGr77W9zbpKebpLF2rWnrULIkPPus01VlitOnTVuwiAjzdXo6fP216c8aGOh0ddfGtm12z9tN3KdxbPl5C640F1HFo6jaqyplWpf54wBob5WSnkKgfyAhASEMbTWUagWrUSp3KafLEhHxKm5p4GNZ1i2WZW21LGuHZVlPXuZxy7KsDy88vt6yLC9dgZNJ9u0zi5SefdaMYiUnO11Rpti/33SriI42uwsBunSB334z6/69LWilJafx2Q2fMbLpSHbO2knt+2szZNsQqvaq6nRpbrH+yHqqfVaNsb+NBaBzxc4KWiIi1yHDI1uWZfkDHwMtgP3ASsuyJtm2velPT2sFlLnwUQf49MJn+fFHc0Jyaqo5PblXL+/cbvcv1q83nd7HjjWzpF26wK23mse8rfH94bWH2bNgD3Xur0OOoByUubUM9R6tR6WulQgI8Y1dorZt88nKT3hkxiPkCslF/rD8TpckIuLV3DGNWBvYYdv2TgDLsr4D2gN/DlvtgZG2OYhxmWVZUZZlFbJt+5Abru+9zp6FwYOhVCmTREqXdrqiTPHUUzB/vvmjPvig9631T0tKY+MPG4n7JI79y/YTEBbADT1vICR3CM3faO50eW514vwJ+k3qx6Stk2hdpjVft/9aYUtEJIPcEbaKAPv+dHs//xy1utxzigDZM2xt3AjlyplFS3PnmrDlbXNoV5Caapacvf+++VyiBHz0kenyniuX09Vdu11zd/FDlx9IPJFInrJ5uPm9m6nauyohuUKcLi1TzN8zn2k7pvHeze/xQJ0HPPawaxERb+KOSZzL/TS2r+M55omWNcCyrDjLsuKOHTuW4eI8istl5tOqV4f33jP3VajgE0HrzBl4912TG3v2hHPn4PBh81iJEt4TtFzpLrZO2sruebsByF8pPyWalqDXrF4M3jKYug/W9bmgleZKY+m+pQB0qtCJ7fdt58G6DypoiYi4iTtGtvYDfz4CuChw8DqeA4Bt28OB4QCxsbGXDWRe6dAh6N3bNJTq2BH69XO6IrdJTDQzoMeOQaNG8OmnpvO7N63HSjiSwJov17Bq2CpO7z1N+Y7lKd64OGH5w+gyrovT5WWa3fG7uf3H21l1aBU77ttBdM5oYnLGOF2WiIhPcUfYWgmUsSyrBHAA6A7c/rfnTAKGXFjPVQc4na3Wa82aBT16mOGeYcPMgngvHjU4fx4mT4bly81oVkgI/N//mWaktWo5Xd21m/30bJa8vQRXqosSzUpw83s3U7ZtWafLynTjNo5jwOQB2NiM6DCC6JzR//0iERG5ZhkOW7Ztp1mWNQSYDvgDX9m2vdGyrIEXHv8M+BVoDewAzgN9M3pdrxIZaebSRoww04ZeKD0d5s0zzex//NGs7S9aFJ57zkwRDhzodIVXL/lMMutHrafqnVUJDA8kd5nc1Bpci9iBseQtl9fp8jKdbdvc88s9fL76c+oWrcuYTmMokauE02WJiPgsy2wQ9EyxsbF2XFyc02Vcn99+g6lT4fHHze2LneG9THo6+PubnNinj8mNt91m1mXddJN5zFscWX+ElZ+uZP2360k9l8pt399Gpa6VnC7LEc/MfgaAFxu/SIC/b7SsEBFxmmVZq2zbjv3H/Qpbbmbb8PHH8OijZshn40bIndvpqq7J/v2mE8WoUTBggGnZEB8PM2ZA27Zm2tCbJJ9NZnSr0exbvI8cwTmo3L0ysYNiKVKriNOlZRnbthm6YihVC1SlUfFG2LatBfAiIm52pbCl43rc6ehRs/B9yhTTtfOrr7wmaNk2jBxpPubONbfr1jXnFYJp3dC1q6MlXpP43fEcWHmASl0qERQRRM6YnFToVIFqfaoRktvL0mIGHTt3jL4T+zJl+xT61+hPo+KNFLRERLKQwpa7pKbCjTeaYaGhQ81wkIf/QktNNUcx1qplSv3iC7Np8vnn4Y47oIyXHevnSnexY9oO4j6NY/uv2wkMC6RM6zIEhgXSeUxnp8tzxOyds+n1cy9OJJ7gw1s+ZEjtIU6XJCKS7ShsZVRqqjnPMCAA/vc/0wOhShWnq7oi24aVK+Hbb+G778xB0IcOQZ48MGGCGYjz8Ix4WTtn72Ty3ZOJ3x1PeMFwbnr2Jmr0r0FgmPf3MLteC/cspMW3LSiXtxxT75hK1YK+cWajiIi3UdjKiM2b4fbb4b77zPRhx45OV/SvFi6Eu++GbdsgKAjatTNHMUZGmsfz5HG2vmth2zb7luwjKCKIAjcUILJoJFElomj+VnPKdyiPf4AXrdx3s9T0VAL8A6gfU5/3bn6Pu2vcTVhgmNNliYhkW17UdtKD2DYMH24aS+3fDwUKOF3RZZ04YRqMzp9vbhcpAoULw5dfwpEj5jidtm3NoJy3SD6bTNxncQyrNoyvG3zN4rcWA5C3XF56z+lNpS6VsnXQGvvbWMp+VJZ9p/fhZ/nxQN0HFLRERBymka1rdeKEaUr688/QooXpiXBxFbkHSEqCX34xOwl//dXMct53n+nsXrKkWfzurea9NI+l7ywl5WwKBasVpO3nbanco7LTZXmEhJQE7p96P1+v/Zp6RethX/40LBERcYDC1rVavtzsNnz7bXjoIY87k6ZBA1i1yuS/++8304Q33OB0VdcnPSWdrZO2Ur5Defxy+OEf4E/5DuWpNagWReoU0Y66C1YfWk2PH3uw/cR2nm34LC80foEcfvqnLSLiKfQT+WqkpsKSJWZ4qHVr+P130z7dYZs2mYXu06aZDBgYCM8+C+Hh0KSJdzUc/bP4PfGsGr6KNV+s4dzRc/T4pQdlby1Lw6cbOl2aR/pw+YecSznHnN5zaFy8sdPliIjI3yhs/ZcdO8wi+DVrYPt2KF7c0aB17JgJWKNGmZL8/aFlS3N/kSLQoYNjpWXY+RPnmdh3ItunbAegbJuyxN4bS6mWpRyuzPMcPXeUs8lnKZW7FB+2+pDU9FTyhHrRDgcRkWxEYetKLnb5HDzYDBl9950JWg5ISDCHP+fPb/LeI4+Y3lgffADdunns+vyrcv74eY5uPErxRsUJyRVC4olEGjzVgJoDapIzJqfT5Xmkmb/PpNfPvSgWVYxldy0jMijS6ZJERORfKGxdjm2bxU6jR5upw2+/hejoLC0hLQ1mzTIjWD//bM4l/PhjqFcPtm6FsmWztBy3sm2b/cv2E/dpHBvHbSQoIoiHDz6Mf4A//Rb3c7o8j5WSnsJzc57jrSVvUTFfRb5o+4XWrYmIeAGFrcuxLKhQAV59FZ54IssXP734omnZcPSoOV6xVy/zcbE0bw5au+bsYsYjMzi89jCBEYHUuLsGsQNjs3W7hqtx6Owh2n/XnpUHV3JPzXt49+Z3CQ0IdbosERG5CgpbF6WlwSuvmCN3WraEZ57Jskvv3g2TJ8OQISZMnTxpdhX27GnW4wcFZVkpmeLYpmMEhAUQVSwK/yB/bJfNrZ/dSpXbqxAU4eV/uCySOyQ34YHhjO8yns4Vs+fRQyIi3sqybc/txxMbG2vHxcVl/oV27TLJZskSePhheOedTL/kqVMwfryZoVy40Ny3YQNUqmRmMb19dig9JZ0tE7aw8pOV7Jm/h9hBsdz68a1c/O9N01//7di5Y7y68FVeavwSOYNzYtu2/t5ERDyYZVmrbNuO/fv9GtkaOxYGDjRfjxkDPXpk+iWXLDGtGVJSoHx5M1t5++2X1t97++/TRW8sYvkHy0k4nEBU8SiavdGM6v2qAwpZV8O2bUauG8nDMx7mbPJZGhdvTIfyHfR3JyLyb2wb0hIg6QgkHjafg/NDfufbBmXvsDVrlkk5N95oFsNnwm5D24bFi81C9woV4IEHoEYN03C0e3fztbf/DrVdNnsX7yWmQQyWZXF672kKxxY2bRtuLoWfv2c1fvVk209sZ+CUgczZNYf60fUZ3nY4FfNVdLosERHnnVwF5/ZcCFNHIOkwhJeAik+YxyeVhHO7//qamC4KW45r1sykoG7dIId7/yq2bjVvPWqUWZMVGmqCFkBwMPzvf269nCNSElJY9fkq4j6J4+SOk/Rb0o/oetG0/qg1lp+XJ0iHPDbzMVYdXMVnt35G/5r98bMUVEXEB6WdN6Ep9SzkunDMye9fwcm4v45MhRaF5vPM48v7w6k1F97AgqC8UOjmS+9ZdrAZ4QgpCMEFILgghBbJyj/VFWnNlhvFx0NUlPm6XTtzqk/z5mYnYYcOprO7L0hNTGXF0BUs+d8Szh8/T0yDGGLvjaVC5wrkCMre+f16LN23lMIRhSkWVYz9Z/bjb/lTKMJzztsUEbkq6Ul/HXVKOgIp8VDxMfP4umdhz/fm/rSz5r6QQtDxoPl6QQc4tsiEpIthKWcFqPysefzkKrD8zWNB+cADjyXTmq1Mcv48TJhgRrBmzjQN54sVMyNXw4Z51BnVGXZxgbbtslny9hIKxxam0QuNKFrX+aOLvNHppNM8PftpPo37lN7VevN1+68pGqm/SxHxIOnJ4BcAlh/Eb4TjS01Yuhimko5AkxngHwRrHodtQ//6essPyj9kglFQPsgTeylIBReAkMKXntvwJ/P8K8ldM3P+jFlAYes67dkDzz8PP/1kOrzHxMBjj5lm8wDlyjlbnzulnEsh7tM4tkzYQp95fQgMC2TQhkGE5Q9zujSv9fPmnxkydQiHEw7zQJ0HeLnpy06XJCLZRXoKJB+9NAqV70YIjIIj82D7Z5fCVOJhSI2Hdr9DeEk4+Cusfdy8R0AUhBQwgSntnAlbxbpBrqp/ClIFISj/pRGo8g8AD1y5Lh9eNqGwdZVsG9atg+RkqFMHQkLg11/NIveePaFhQ/Dzsf9OUs+nsvLTlSx5awnnjp6jVMtSJJ5MJCx/mIJWBnwW9xn3TrmXqgWqMqHbBGoVqeV0SSLiC9LOw5mtl0adLq57KnUXRFWGg1NhSU9IOfnX1zWfD/lvguQTcGr1hem7ylCwuQlNOS6sgSnVzwSq4PzgH/zP6+erbz7kHxS2/sO+fWaj4qhRsHGjWVM/a5Y5p/DQIbevq/cYJ7ad4OuGX3Pu6DlKtihJ4xcbE31j1h5Z5EvSXekcPXeUQhGF6F65O8lpyQyqNYgA/wCnSxMRT+VKh+Rj4BcIQblNGPr9y78GqaQjUOV5s+vu1FqY+bewkyMCCjQxYSs0Bop1vzTqFHxhZCpnZfPcmM7m40qC8pgPuWY+GhXcY8gQ+OQTM6pVr575ukuXS4/7WtBKTUzl6IajFKlVhFylclG2XVmq9a5GTIMYp0vzauuPrKf/5P4kpSUR1z+OqOAoHqj7L0PpIuL7XGmmTcGZrWaReO4akHIaFnX503qoY4ANVV+FSk+b6bq1T4B/iBl9CikIEaUhIKd5z5wVzbqni48FF4AcfzrWK6oS1PrYiT9ttudjceH6paTA9Ommx+lnn0FkpAlY+fPDHXdAqVJOV5h5UhNTWTVsFYvfXEx6SjoP7XuIgNAA2n3ezunSvFpiaiL/N///eHvp2+QKzsV7N79HDg/cPSMimcS2zchU2nkILw62CxbeBmc2Q8Lv4Eo1zyt9D9T+zASj1DNmfVTeepcWkue70TwvtCh0OWOm9S7XoDEwCqI7ZtWfTq5Btv7Jb9uwfLmZIvzuOzhxAvLmhU2boG5dE7J8WWpiKquGr2LxG4tJOJxA8SbFafxiYwJCNbWVUTtP7aTlty35/dTv9K3Wl/+1+B95QjX8LuKTXGmXFoFvHQonVsLZbWbUKjUeCt8KjX8xC8DTzkFkBSjaHiLKQWQ5iCxvXusXADcvu/J1LD8IiMj0P464X7YOW1u2mNGr4GDTB6tnT3MGdUA2yRqHVh9i+oPTKd64OJ2/60zxRsWdLsnruWwXfpYf0ZHRVC1YleFth9O0RFOnyxIRdzm+zISpM1vh7FY4s82sp2p1odnmvvGQsNMEqeI9zOfc1S+9vul0Z+oWR2X7pqY//WQaj0ZGZuplPEJaUhqrv1jN+ePnafxiYwAOrTlEoeo+1AzMIbZt8+36b3l7ydss6LuAqOAop0sSkeuRctpM853Zeml0KukwtFhkHl98B+wZYxaeR14YmYqqeqlx559HuSTbUVPTK+jUyekKMt/FkLXo9UWcPXiWks1LYrtsLD9LQcsNdpzcwcBfBjJ712zqFa1HfFK8wpaIJ0tPNmum/hyoan4IAeGw8VXYfOE8NSuHWT8VUdZ0R/cPhmqvQ413zHqqy62bUtCSy9B/FT5u5+ydTOg9gbMHzhLTIIaO33akeJPiWN5++rUHcNku3lr8Fi/Nf4lA/0A+af0J98Teo/MMRTyBbUPiATPNd3YrFO1odujt/AaW32UWq18UXBAqHoKAMlCil+k5FVHWHHLs97d1JWHanS3XTmHLB6Ulp5F0KonwguFEFY8id+ncdBjRgRJNSyhkuZGFxYI9C7i1zK182OpDCkcU/u8XiYh7pZ4xgSq0iGmhcGIlrLjHjFilnbv0vJCiULQt5KoOlZ65tDg9ogwE5rz0vKgq5kPEjbL9mi1fkpacxtqv17LwtYUUrFqQHpN7OF2SzzmTfIYX5r7AA3UfoHhUcRJTEwkJCHG6LBHf5ko1U38B4ZB01BxofHFxetJh85xan0CZe+HMdlj1AESWvRCmLnwOKezTx8GIZ9CaLR+WnpLOmq/XsPDVhZzZd4ai9YpS+/7aTpflcyZsmcCQX4dw8OxBKuarSP+a/RW0RNzNlQY7v760lurMVrO7r+LjprmnfzDs/9mEqMKtLoWpPHXM6yPLQJNfnf0ziPyNwpYPWPreUmY/OZuidYvS7ot2lGxRUtOFbnTgzAHum3ofP2/5mRsK3MBP3X6idhGFWZHrFv8bnN50aT3Vma2Qp7bpbm75w5pHzUhWRBkzpRdzGxRsYV4bEAmdjzlbv8g1UtjyQukp6awdsZao4lGUalGKmgNqUrBqQUrdXEohKxO8tfgtpu6YypvN3+Shug/pPEOR/+JKh/N7TJi6uOMvRyhUv7DLb3F3E7bAnNcXWdbs+gOzw6/Nlgu7/TTtJ75Ba7a8SHpqOutGrGPhqwuJ3x1Ptb7VaP9Ve6fL8kkbjm4gzZVGtYLViE+K58T5E5TK7cNnNolcj/QUOP0bnFpvjqWp+Li5f96tcPBPU3kBUWaHX6OJ5vaxJebImYjSfz27T8TLac2Wl9s0fhMzH5tJ/O54CtcqTOuPW1O6VWmny/I5iamJvLLgFd5a8hY3FbuJ2XfOJio4Sn2zRC7+j7llwa5vYdsncGoNuJLN/f4hUP5h02eq9ACI7nRhx19ZCMr3155UF8/6E8kmFLY8mCvNhW3b+Af4k3gykdC8oX+ELE0Xut+cXXO455d72HFyB72r9ubtlm87XZKIcxIPwYkVppXCxc+t10NYNKQnmv5TZYeYtVa5ql/oSXXhV0pRjbiL/JmmET2QK83F+lHrWfDKAuo+VJfag2vjSndh+VkKWZlkyrYptBnbhlK5SjGszTCalWzmdEkiWSf1DJyIM7v6QovA3h9h0W3mMcvfLFLPUxsqPgXhxR0tVcSTaRrRC/w5ZJ36/RSFahQiT9k8APj5a6Gou9m2zf4z+4nOGU3LUi15t+W7DIwdqHYO4vtSz5ipwIsjVme2APalXlV560KN9y6MWlXTuiqRDNLIlgcZ3208G8dtpFCNQjR6sRFl25TVSFYm+f3k79w75V42HN3A5sGbyRmc879fJOJtbBec3X4hVK0w032l+pnDlsdHQXB+058qdy0TrPLWgcAop6sW8Voa2fJArjQXv439jdK3lCYsXxi176tNlTuqULatQlZmSU1P5d2l7/Li/BcJ8AvgjeZvEB4Y7nRZIu6RmmC6rAMs6ABH5ppRLDC7/8qGma8Dc0KHA+Z4G/2sEcl0ClsOuBiyFry8gJPbT9Li7Rbc+MiNxDTQAaeZ6WTiSZqMaML6I+vpWL4jQ1sNpUhkEafLErk+KfFwMu7SqNWJleZImltWmseDC0DxO8yIVZ7aZmegn/+l14fqLE+RrKKwlcV+G/Mb81+az4ltJyhwQwG6/tSV8u3LO12WT3PZLvwsP3IF5yK2UCwvNnqRjhU6Ol2WyNVLT4JT60zn9dJ3m/uW94d9483XEWWhQBPIV//Sa2oPy/o6ReSyFLaygG3bf0wLbv5xM/5B/nT9sSvlO5TH8tMQfmaavHUyj818jKl3TKVErhJ82f5Lp0sSuTrHlsLuC4vY49ebw5gBirSBkIKmp1XpAZAnFgJzOVuriPwrha1M5Ep3sXHcRha+upCu47uSt3xe2n3ZjqDIIIWsTHbo7CHun3Y/4zeNp3L+ypxNOet0SSL/ZNtwfv+lqcCTK6HmUIiqZI642TUK8tSC8o9cmA6sZaYHAfLVc7Z2EblqCluZwJXuYtMPm5j/f/M5vvk4+SvnJ/FUIgDBUcEOV+f7hq8azuMzHyc5PZnXmr7Gozc+qvMMxTMknzSfg3LDyVUwrw0kHTb3+QVAVFVIPW1uF+sBJXrpfEARH6Cw5WaudBdf1PmCQ6sOka9SPm4bdxsVO1fUSFYWWnt4LbGFY/mszWeUzq0jjcQhrvQ/LV6/8JGwA6q+BpWegtBiUKjlpbYLuaqCf9Cl1/sHOle7iLiV+my5ge2y2Tl7JyWbl8SyLJa+u5SIIhFU6lJJISsLJKUl8eqCV2lTtg11itYhOS2ZQP9Atc+QrONKhzObTaAKiICYLmaN1bgIc3ZgSJFLuwILtzLBSkR8jvpsZQLbZbPpx03Mf2k+xzYeo8+CPhRrWIx6D2stRVaZt3seAyYPYPvJ7fj7+VOnaB2CcgT99wtF3GHj63BoumnBkHbO3FewhQlbfgHQZJrZKag2CyLZmsLWdbBdNpt/2sz8l+ZzdMNR8pbPS6cxnYi+Mdrp0rKNE+dP8NjMx/h67deUzFWSGT1n0KJUC6fLEl+UfOJPhzGvgJST0HKJeezUWkhPhpL9/tTP6k9T1wUaO1GxiHgYha3rkJaUxq+DfyU4VzCdRneiUrdKOrswi41YN4KR60byRP0neL7R84QG6Ow2cYO083ByNeS70SxMX/MEbH7rwoMW5KxgApUrDfxyQP3v1IFdRP6T1mxdBdtls2XiFtZ/u54u47rgl8OP41uOk7tMboWsLLTr1C72nt5Lo+KNSE1PZeuJrVTOX9npssSbnT8AB3+91IH99Aaw06HNFogsB4dnmfCVpzbkrgEBkU5XLCIeTGu2roNt22yduJX5L83n8NrD5C6Tm9N7T5OrZC7yls/rdHnZRporjfeWvscL816gaGRRtgzZQoB/gIKWXD3bhnO7Lk0HlugFuaqZtVYrBpimoHlqQ5G25nPIhWOcCjY3HyIiGaCwdQVnD55lzK1j/ghZHUZ2oEqPKvjl0EhWVlp5YCUDfhnA2sNraVeuHR+1+gg/9R2Sq3V+P6wYCCeWmbVXAH5BkKu6CVsFmkHb7RBeStOBIpJpFLb+xLZtTu08Re5SuQkrEEbOmJzUfaguVW5XyHLC2sNrqftlXQqEFeDHrj/SsXxHtXOQK0s8ZKb9Ds2EXDdAhUchKC+c3wdF2l9awB5V2ewUBAgIhwD1YhORzKWwhQlZ237ZxvwX5xO/O54Hdj1AUGQQ3Sd2d7q0bGlP/B6KRRWjaoGqfHjLh/S8oSc5g3M6XZZ4qvUvwL6fzHorMAErvLj52j8YWq9zrDQREcjmYcu2bbZP2c68F+dxaNUhcpXMRct3WhIQqqNdnHA44TAPTHuAyVsns2nwJopHFWdw7cFOlyWewpUOp1bD4ZlwdgfU/crcf2aLOS+wRE/T4ypXNR1xIyIeJVuHrUOrDzG27ViiSkTR7qt23NDzBvwD/J0uK9tx2S6+WP0FT8x6gsTURJ676TkKR6gJpFxweDZs/xSOzIGUU+a+XNUhLRFyhKj9goh4vGwdtgrXLEyPyT0odXMphSyHpKan0uLbFszfM58mxZvwWZvPKJunrNNliVNSTsHhOWb0quKTZjrw3B44sRyKdjAjVwWbQXD+S69R0BIRD5etwxZA2Tb6xe4El+3Cz/IjwD+AG6NvpE+1PvSu2lsL4LOjxCOw7UOzsP3UKrBdkCMcirY3YavEnVCyr0KViHgtLWyQLDd/93wqf1KZZfuXAfBas9foU62PglZ2YNsQvwG2vAf7J5r7LAs2vWV2CFZ6DpovhNtOmgObwXRq138bIuLFMjSyZVnW/4C2QArwO9DXtu34yzxvN3AWSAfSLtddVXzfqcRTPD7zcb5Y8wUlokqQmp7qdEmSVXZ/B4emmunBxEPmvlJ3m9Gr4Pxw2ynThkFExAdldBpxJvCUbdtplmW9CTwFPHGF5zaxbft4Bq8nXmr8pvEM/nUwJ86f4PEbH+eFxi/oPENflXYOji6EhJ1QdpC5b+sHkLAdCjSHQi3M2quwmEuvUdASER+WobBl2/aMP91cBtyWsXLEV/1+8ndicsYwved0qhWs5nQ54m6nN8P+n826q+NLwJVizhEsdTf4B8JNEyA4n1oyiEi25M6ffP2AqVd4zAZmWJa1yrKsAW68pnioNFca7y59l583/wzAIzc+wrK7lilo+YqEXbBjOKTEm9v7J8K6Z8xuwnL3Q5Pp0PGwCVoAIQUUtEQk2/rPkS3LsmYBBS/z0DO2bU+88JxngDRg9BXepr5t2wcty8oPzLQsa4tt2wuucL0BwACAmJiYyz1FPNyqg6sY8MsAVh9azV3V76JjhY7k8Mv2G1+9W2oCHJ5hRq4Oz4SE3839wQWhaDszglWyrwlVIiLyF5Zt2xl7A8vqDQwEmtm2ff4qnv8ikGDb9tv/9dzY2Fg7Li4uQ/VJ1klISeCFuS/w/vL3yR+Wn6GthtK5QmftMvRG6Snm8OaAnJCrKpzeBFMqmZYMBZpAweZm3VVkee0UFBG5wLKsVZfbBJjR3Yi3YBbEN7pS0LIsKwzws2377IWvWwL/l5Hrimea8fsM3l32LvfUvIc3mr9BVHCU0yXJtTi96dLI1dF5ZqF7id5Q7xuIrAAtFkOeWpcOcRYRkauSoZEty7J2AEHAiQt3LbNte6BlWYWBL2zbbm1ZVkng5wuP5wDG2Lb96tW8v0a2PN+RhCPEHYzj1rK3Yts2G45uoEqBKk6XJVcj8TCc3Q75G5rbk8pAwg6IKHOhU3sLM4oVqEPARUSuRqaMbNm2XfoK9x8EWl/4eidQNSPXEc+TmJrI0BVDeX3R61hY7H1oL+GB4QpaniztPBxdYEauDs+E+N8gKA90OmoWr9f7BkKLQlgxpysVEfEpWrUs1yTNlcaItSN4Yd4LHDh7gFalW/Heze8RHqg+SR7HlQ6n1pg1V34BsP552PIO+AVCvgZQ9XXT84oLa67y1Xe0XBERX6WwJddk87HN3D35buoUqcPoTqNpVLyR0yXJnyXsgsOzLoxezYaUk+b4m/wNoNRdZmowf0PIoYayIiJZRWFL/tPCPQtZtHcRTzV8iioFqrD87uXUKlxLuww9QUq8aSAanB+OLYGZF0anQoqYlgwFmkNUJXNfzgrmQ0REspTCllzRhqMbeGr2U/yy7ReKRhZlSO0hRARFULtIbadLy74utmS4uGvw5Eoo/whUfwtyx0LND9SSQUTEwyhsyT8cTjjMU7OfYsTaEUQGRfJ6s9e5v879OsvQCbYNycfNUTe2DZPLwPm9ZkF77tpQ6Rko2sE81z/QdG8XERGPorAl/2DbNpO2TuKReo/wZIMnyROax+mSshfbhhPLYe942Dce/IKg7VYzUlX5WQjKe6ElQ5TTlYqIyFVQ2BLOp57nw+UfsnjfYiZ1n0ShiELsfXAvYYFhTpeW/ewcAeufg/P7zA7Cgi2haHuwXWY0q3R/pysUEZFrpLCVjaW50vh6zde8OP9FDp49SNuybUlISSAiKEJBKyu40uHYIjN6Vf4hCC8JARGQqzpUfRWKtNXolYiID1DYyqa2HN9Ch+86sPXEVuoVrcd3nb+jYbGGTpfl+1xpprHo3h9g/0+QdBT8g820YHhJiO5kPkRExGcobGUzpxJPkSskFzE5YygaWZQ3m79Ju3Lt1MYhM7lSIemI6c6eehrmtjTrsIrcCtG3QeHWEKCmsCIivkphK5tYf2Q9T81+ii3Ht7B58GZCA0KZdecsp8vyXekpprnovvGwfwJE3QDN55njcZrNMW0a1FhURCRbUNjycXvi9/D8vOf5dt235AzOyVMNniIjh4/LVdj4Omx604xiBURCkXYQ0/XS4/lvcq42ERHJcgpbPmzt4bXU+aIOFhaP3fgYTzZ4klwhuZwuy7ekJcKhabDvR4gdCoG5TDf36I5mirBgc/APcrpKERFxkMKWjzmXco61h9dSP6Y+NxS4gacaPMVd1e8iOme006X5jrTzcPBXs8j94BRIO2emB09vhnw3mjMIS93ldJUiIuIhFLZ8RGp6Kl+u+ZKX5r9EYmoi+x/eT3hgOC82ftHp0nxD6llzDmFYNJzfD4u6mBGs4r0g5jbI3wj89M9JRET+Sb8dvJxt24zfNJ5n5jzD9pPbaRDTgDebv0l4oHa3ZVjKaTgw2SxyPzjNNBdt8D1EloWWSyF3LfDzd7pKERHxcApbXm7t4bV0Hd+VSvkqMbnHZG4tc6vaOLjDysHw+xfgSoGQIlBmIMR0u/R43rrO1SYiIl5FYcsLrT28liX7ljCo1iCqF6rOrF6zaFy8Mf4aZbk+ScfhwEQ4OBXqjzXH5ESUhrJDzCL3vHXMUTkiIiLXQWHLi+w8tZPn5j7HmN/GkD8sP3dWvZPwwHCalWzmdGneJ/nEpYOej8wFOx3CSkDCbogsY47PERERcQOFLS9w4vwJ/m/+//Fp3Kfk8MvBUw2e4vH6j2td1rVKPGQOdA4tAqc3wsqBEFEGKj5hRrByVQNNwYqIiJspbHmBsyln+WLNF/St1pcXGr9A4YjCTpfkPc7vh30/mVGsY4ug7H0Q+wHkrQ+t10POygpYIiKSqRS2PFBKegqfr/qc5QeWM7LjSIpHFWfvg3vJE5rH6dK8y7y2cPAX83XOylDlxUud3P38IaqKY6WJiEj2obDlQVy2ix82/sAzc57h91O/06hYIxJSEggPDFfQ+i8JO2Hvj3BiBTQYZ0ar8tQ2uwajO0PO8k5XKCIi2ZTClofYdmIbt/94O6sOraJK/ir8evuv3FL6FrVx+Dfn9sLu0WaK8NRqc1/uWEg5BUG5ocpzztYnIiKCwpbjzqeeJzQglILhBbEsi5EdRnJ7ldvVxuFKTm8x5w+GFIDjy2Dd05CnLlR/24xghRd3ukIREZG/UNhyyO8nf+fZuc/y25HfWDtwLZFBkay4e4VGsv7Ots3OwYttGk5vhKqvQaWnoEhbaL8HwmKcrlJEROSKFLay2JGEI7yy4BU+W/UZgf6BPFT3IVLTU8nhl0NB6+9caTCtBsT/BliQ/yaoORSiO5nHc4RADgUtERHxbApbWWjNoTU0/LohSWlJ9K/Rn+cbPU+hiEJOl+UZbNusu9r7A5w/CDeONAc7F2kLZQZB0Q4QUtDpKkVERK6ZwlYmS05LZsvxLVQtWJUqBarQv0Z/7q11L2XzlHW6NM8QvwF2jTDThOd2g+UPBVuAK9Ucm1P1VacrFBERyRCFrUzisl2M/W0sz819jrMpZ9n9wG7CAsN475b3nC7NWbbLLGzPWRECo8xROVs/MAGr8vNQtB0Eqc2FiIj4DoUtN7Ntmxm/z+DJ2U+y9vBaqhaoyqe3fkpoQKjTpTnHlQ7HF19Y5P4jJB6EOl9Bqb5QsjeU6Gl2GIqIiPgghS03W3VoFbeMvoUSUSUY3Wk03St3x8/yc7os56Scgl8qQNIR8A+GQq0g5jYo0sY8HhDpbH0iIiKZTGHLDbaf2M6y/cvoVbUXsYVj+bHrj7Qp24ZA/0CnS8tarlQ4Ms+0aLD8odYnZsSqRC/IXQsKt4YAHZ4tIiLZi8JWBhw6e4j/m/9/fL76c3IG56RThU6EBYbRqUInp0vLWkcXwc6vYf8ESDkJOcKhWLdLj1f/n2OliYiIOE1h6zqcTjrN/5b8j/eWvUdKegoDYwfy3E3PERYY5nRpWefUOshZybRnODTVjGYVaWemCAu2ND2wRERERGHrehxOOMybi9/ktoq38XKTlymdu7TTJWWNlHjYPQZ+/9L0xGo02ay9qvC42UnoH+R0hSIiIh5HYesqpLvSGfPbGFYeXMmHrT6kXN5y7HpgF0UjizpdWtZIiYe4IWYnYXoSRFU1ndzz1TePB+Z0tDwRERFPprD1L2zbZtqOaTw5+0nWH1lPzUI1OZdyjrDAMN8PWucPwpktULCp2TEYvwFK9oVSd0GuGqCjhURERK6KwtYV/H7yd+6adBfz98ynVK5SfNf5O7pU6uLbbRxcqXBgipkmPDTVNBftcMCsy2q1RgFLRETkOihs/U1qeioB/gFEBUdxKOEQH7X6iP41+/t+G4c942DV/aYfVkghqPAYlOxnghYoaImIiFwnha0LDp49yEvzXmLtkbUsvWspeULzsHnwZt8dyUo7Zzq6560LkeVMwMpbF0reBYVbXQpZIiIikiHZ/jdqfFI8by1+i/eXvU+aK42BsQNJTksmJCDE94KWbcPJOPj9C9g9FtLOQuUX4IYXIX9D8yEiIiJula3D1ppDa2g2shmnkk5xe5XbebnJy5TMVdLpsjKHbcPMBnB8CfiHQEwXs9g9nwKWiIhIZsrWYatS/kp0KN+B+2rfR/VC1Z0ux71sFxyeDYdnQLW3zJqrou2gxJ1QrLvaNYiIiGQRy7Ztp2u4otjYWDsuLs7pMrzLub2w8xvY+RWc22POJmy9HkJ9vFWFiIiIwyzLWmXbduzf78/WI1s+59BMmHszYEPB5lD1DYjuAP7BTlcmIiKSbSlsebPTm0xPrMhyUHqA6ehe5QUzVRhewunqREREBIUt75N6FvZ8b0LWiWXgFwDlHjCP5Qg1YUtEREQ8hsKWt1lyBxyYDDkrQvV3oEQvCM7ndFUiIiJyBQpbnizpKOz6FnaNgMZTIbQIVHoWKj0Neeqoq7uIiIgXUNjyNK50ODQddn4J+yeBnQZ565ngFVoE8tZ2ukIRERG5BgpbnsKVatZfJR2BBW0hMDeUu980Hs1Z0enqRERE5DopbDkpPQn2/WwWu/vlgCbTILQwNJsPeWqDrx9+LSIikg0obDnh9CbY/hnsHgUppyCsuBnBsm2zDit/A6crFBERETdR2MoqKfGmuah/MBycCjuGQXQnE7IKNAVfO/RaREREAIWtzGXbcHSBmSbc9wPUGgYl74TS/aFkXwjK7XSFIiIikskUtjKDKw02v21CVsIOCIiEEr0hdw3zeECks/WJiIhIllHYchdXKpzeCLmqgeUPe74zi90rPwcxt5nu7iIiIpLtKGxl1JntpifWzhGQdhY6HoKACGi5GHKEOV2diIiIOExh63odXwFrHzNrsix/KHyrWezuH2IeV9ASERERFLb+v707i7WrLMM4/n9oIbQFBBm0dGBQQiBEAWsBib0QUKgMojeQiAYvIAQU1MQgeqHxwmhAvVGS2iokIgQZEiQNUxyiFyBtARmKCligLUgNk4BhfL3Yy3BS2+5TTrff2vD/JTv77OGc9eTNPrtP17f2OpNXBU+vHJSodx00+FThS+vhg9+F/T8PM2a3TihJknrIsjXMy0/Dmivg4aXw7J8HB7ofdRns9gE46a/+fUJJkrRFlq0tWfEleGgJvPEyvPtD8OGfwD6nv/m4RUuSJA0xpTNpJvlWknVJ7u4uizfzvOOT/CXJQ0kunMo2R+rFx2H1JYM/Bg2w416Dc2KdcBccvwIOOAd22LVpREmSNF62xZ6tH1bVxZt7MMk04MfAccBa4M4kN1TVA9tg21P3+iuw7teDc2I9eTPUG7DnR2GPhXDIN1unkyRJY+7/sYy4EHioqh4BSHIVcArQvmw99yDctghe3gAz5sDBF8H7zoSd9m+dTJIkvU1si7J1XpLPASuAr1bVMxs9Pgd4fMLttcAR22C7U7fz+2HOSTDvMzD7E7DdtNaJJEnS28zQspXkNuC9m3joG8ClwHeA6q4vAb6w8Y/YxPfWFrZ3FnAWwPz584fFm5rtpsORy0a7DUmS9I42tGxV1bGT+UFJfgrcuImH1gLzJtyeC6zfwvaWAEsAFixYsNlSJkmSNA6m+mnEiWfyPBW4bxNPuxM4IMl+SXYATgNumMp2JUmSxsVUj9n6fpJDGSwLrgHOBkiyN7C0qhZX1WtJzgNuBqYBP6uq+6e4XUmSpLEwpbJVVWds5v71wOIJt5cDy6eyLUmSpHE0pWVESZIkbZllS5IkaYQsW5IkSSNk2ZIkSRohy5YkSdIIWbYkSZJGyLIlSZI0QpYtSZKkEbJsSZIkjZBlS5IkaYQsW5IkSSNk2ZIkSRohy5YkSdIIWbYkSZJGyLIlSZI0QpYtSZKkEbJsSZIkjZBlS5IkaYQsW5IkSSOUqmqdYbOSbAAe7W7uAfyzYZxx4IwmxzkN54yGc0aT45yGc0aTMw5z2qeq9tz4zl6XrYmSrKiqBa1z9JkzmhznNJwzGs4ZTY5zGs4ZTc44z8llREmSpBGybEmSJI3QOJWtJa0DjAFnNDnOaThnNJwzmhznNJwzmpyxndPYHLMlSZI0jsZpz5YkSdLY6XXZSjIvyW+TrE5yf5LzW2fqoyQ7JvlTknu6OX27daa+SjItyV1Jbmydpa+SrElyb5K7k6xonaePkuya5JokD3bvT0e1ztQ3SQ7sXkP/vTyf5ILWufomyZe79+37klyZZMfWmfomyfndfO4f19dQr5cRk8wGZlfVqiQ7AyuBT1XVA42j9UqSALOq6oUk2wN/BM6vqtsbR+udJF8BFgC7VNWJrfP0UZI1wIKq6vv5bJpJcjnwh6pammQHYGZVPds4Vm8lmQasA46oqkeHPf+dIskcBu/XB1fVv5NcDSyvqsvaJuuPJIcAVwELgVeAm4BzqupvTYNtpV7v2aqqJ6pqVff1v4DVwJy2qfqnBl7obm7fXfrbohtJMhf4JLC0dRaNryS7AIuAZQBV9YpFa6hjgIctWps0HZiRZDowE1jfOE/fHATcXlUvVdVrwO+BUxtn2mq9LlsTJdkXOAy4o3GUXuqWx+4GngJurSrn9L9+BHwNeKNxjr4r4JYkK5Oc1TpMD+0PbAB+3i1JL00yq3WonjsNuLJ1iL6pqnXAxcBjwBPAc1V1S9tUvXMfsCjJ7klmAouBeY0zbbWxKFtJdgKuBS6oqudb5+mjqnq9qg4F5gILu12v6iQ5EXiqqla2zjIGjq6qw4ETgHOTLGodqGemA4cDl1bVYcCLwIVtI/VXt8x6MvCr1ln6JsluwCnAfsDewKwkn22bql+qajXwPeBWBkuI9wCvNQ31FvS+bHXHIF0LXFFV17XO03fdcsbvgOPbJumdo4GTu+ORrgI+luQXbSP1U1Wt766fAq5ncKyE3rQWWDth7/E1DMqXNu0EYFVV/aN1kB46Fvh7VW2oqleB64CPNM7UO1W1rKoOr6pFwNPAWB2vBT0vW92B38uA1VX1g9Z5+irJnkl27b6eweAX+MGmoXqmqr5eVXOral8GSxq/qSr/B7mRJLO6D6PQLY19nMFufHWq6kng8SQHdncdA/ihnc07HZcQN+cx4MgkM7t/745hcGyyJkiyV3c9H/g0Y/h6mt46wBBHA2cA93bHIwFcVFXL20XqpdnA5d0nfrYDrq4qT22gt+I9wPWD932mA7+sqpvaRuqlLwJXdEtkjwBnNs7TS90xNscBZ7fO0kdVdUeSa4BVDJbG7mKMz5I+Qtcm2R14FTi3qp5pHWhr9frUD5IkSeOu18uIkiRJ486yJUmSNEKWLUmSpBGybEmSJI2QZUuSJGmELFuSJEkjZNmSJEkaIcuWJEnSCP0HQpdWwrC15sgAAAAASUVORK5CYII=\n",
      "text/plain": [
       "<Figure size 720x720 with 1 Axes>"
      ]
     },
     "metadata": {
      "needs_background": "light"
     },
     "output_type": "display_data"
    }
   ],
   "source": [
    "fig, ax = plt.subplots(1, 1, figsize=(10,10))\n",
    "pure = time_regression(vertex_choices, times_p, 'red')\n",
    "compiled = time_regression(vertex_choices, times_c, 'green')\n",
    "compiled_parallel = time_regression(vertex_choices, times_cp, 'blue')\n",
    "pure_queue = time_regression(vertex_choices, times_pq, 'purple')\n",
    "compiled_queue =  time_regression(vertex_choices, times_cq, 'orange')\n",
    "print(np.exp(pure.mean()-compiled_queue.mean()))"
   ]
  },
  {
   "cell_type": "code",
   "execution_count": 18,
   "id": "a21d2adf",
   "metadata": {},
   "outputs": [],
   "source": [
    "import ast\n",
    "import dis"
   ]
  },
  {
   "cell_type": "code",
   "execution_count": 20,
   "id": "e713dcd7",
   "metadata": {},
   "outputs": [
    {
     "name": "stdout",
     "output_type": "stream",
     "text": [
      " 10           0 BUILD_MAP                0\n",
      "              2 STORE_FAST               4 (dist)\n",
      "\n",
      " 11           4 BUILD_MAP                0\n",
      "              6 STORE_FAST               5 (prev)\n",
      "\n",
      " 12           8 LOAD_GLOBAL              0 (list)\n",
      "             10 LOAD_GLOBAL              1 (range)\n",
      "             12 LOAD_GLOBAL              2 (len)\n",
      "             14 LOAD_FAST                0 (verts)\n",
      "             16 CALL_FUNCTION            1\n",
      "             18 CALL_FUNCTION            1\n",
      "             20 CALL_FUNCTION            1\n",
      "             22 STORE_FAST               6 (Q)\n",
      "\n",
      " 13          24 LOAD_FAST                6 (Q)\n",
      "             26 GET_ITER\n",
      "        >>   28 FOR_ITER                26 (to 56)\n",
      "             30 STORE_FAST               7 (v)\n",
      "\n",
      " 14          32 LOAD_GLOBAL              3 (np)\n",
      "             34 LOAD_METHOD              4 (float64)\n",
      "             36 LOAD_CONST               1 (1000000000.0)\n",
      "             38 CALL_METHOD              1\n",
      "             40 LOAD_FAST                4 (dist)\n",
      "             42 LOAD_FAST                7 (v)\n",
      "             44 STORE_SUBSCR\n",
      "\n",
      " 15          46 LOAD_CONST               2 (-1)\n",
      "             48 LOAD_FAST                5 (prev)\n",
      "             50 LOAD_FAST                7 (v)\n",
      "             52 STORE_SUBSCR\n",
      "             54 JUMP_ABSOLUTE           28\n",
      "\n",
      " 16     >>   56 LOAD_CONST               3 (0)\n",
      "             58 LOAD_FAST                4 (dist)\n",
      "             60 LOAD_FAST                2 (source)\n",
      "             62 STORE_SUBSCR\n",
      "\n",
      " 17     >>   64 LOAD_GLOBAL              2 (len)\n",
      "             66 LOAD_FAST                6 (Q)\n",
      "             68 CALL_FUNCTION            1\n",
      "             70 POP_JUMP_IF_FALSE      248\n",
      "\n",
      " 18          72 LOAD_GLOBAL              5 (get_mindist)\n",
      "             74 LOAD_FAST                4 (dist)\n",
      "             76 LOAD_FAST                6 (Q)\n",
      "             78 CALL_FUNCTION            2\n",
      "             80 STORE_FAST               8 (u)\n",
      "\n",
      " 19          82 LOAD_FAST                6 (Q)\n",
      "             84 LOAD_METHOD              6 (remove)\n",
      "             86 LOAD_FAST                8 (u)\n",
      "             88 CALL_METHOD              1\n",
      "             90 POP_TOP\n",
      "\n",
      " 20          92 LOAD_FAST                8 (u)\n",
      "             94 LOAD_FAST                3 (target)\n",
      "             96 COMPARE_OP               2 (==)\n",
      "             98 POP_JUMP_IF_FALSE      108\n",
      "\n",
      " 21         100 LOAD_FAST                4 (dist)\n",
      "            102 LOAD_FAST                5 (prev)\n",
      "            104 BUILD_TUPLE              2\n",
      "            106 RETURN_VALUE\n",
      "\n",
      " 22     >>  108 LOAD_GLOBAL              1 (range)\n",
      "            110 LOAD_GLOBAL              2 (len)\n",
      "            112 LOAD_FAST                1 (edges)\n",
      "            114 LOAD_FAST                8 (u)\n",
      "            116 BINARY_SUBSCR\n",
      "            118 CALL_FUNCTION            1\n",
      "            120 CALL_FUNCTION            1\n",
      "            122 GET_ITER\n",
      "        >>  124 FOR_ITER               120 (to 246)\n",
      "            126 STORE_FAST               9 (i)\n",
      "\n",
      " 23         128 LOAD_FAST                1 (edges)\n",
      "            130 LOAD_FAST                8 (u)\n",
      "            132 BINARY_SUBSCR\n",
      "            134 LOAD_FAST                9 (i)\n",
      "            136 BINARY_SUBSCR\n",
      "            138 STORE_FAST               7 (v)\n",
      "\n",
      " 24         140 LOAD_FAST                4 (dist)\n",
      "            142 LOAD_FAST                8 (u)\n",
      "            144 BINARY_SUBSCR\n",
      "            146 LOAD_GLOBAL              3 (np)\n",
      "            148 LOAD_ATTR                7 (linalg)\n",
      "            150 LOAD_METHOD              8 (norm)\n",
      "            152 LOAD_FAST                0 (verts)\n",
      "            154 LOAD_FAST                8 (u)\n",
      "            156 BINARY_SUBSCR\n",
      "            158 LOAD_FAST                0 (verts)\n",
      "            160 LOAD_FAST                7 (v)\n",
      "            162 BINARY_SUBSCR\n",
      "            164 BINARY_SUBTRACT\n",
      "            166 CALL_METHOD              1\n",
      "            168 BINARY_ADD\n",
      "            170 STORE_FAST              10 (alt)\n",
      "\n",
      " 25         172 LOAD_GLOBAL              9 (boolean)\n",
      "            174 LOAD_FAST               10 (alt)\n",
      "            176 LOAD_FAST                4 (dist)\n",
      "            178 LOAD_FAST                7 (v)\n",
      "            180 BINARY_SUBSCR\n",
      "            182 COMPARE_OP               0 (<)\n",
      "            184 CALL_FUNCTION            1\n",
      "            186 STORE_FAST              11 (a)\n",
      "\n",
      " 26         188 LOAD_FAST               10 (alt)\n",
      "            190 LOAD_FAST               11 (a)\n",
      "            192 BINARY_MULTIPLY\n",
      "            194 LOAD_FAST                4 (dist)\n",
      "            196 LOAD_FAST                7 (v)\n",
      "            198 BINARY_SUBSCR\n",
      "            200 LOAD_CONST               4 (1)\n",
      "            202 LOAD_FAST               11 (a)\n",
      "            204 BINARY_SUBTRACT\n",
      "            206 BINARY_MULTIPLY\n",
      "            208 BINARY_ADD\n",
      "            210 LOAD_FAST                4 (dist)\n",
      "            212 LOAD_FAST                7 (v)\n",
      "            214 STORE_SUBSCR\n",
      "\n",
      " 27         216 LOAD_FAST                8 (u)\n",
      "            218 LOAD_FAST               11 (a)\n",
      "            220 BINARY_MULTIPLY\n",
      "            222 LOAD_FAST                5 (prev)\n",
      "            224 LOAD_FAST                7 (v)\n",
      "            226 BINARY_SUBSCR\n",
      "            228 LOAD_CONST               4 (1)\n",
      "            230 LOAD_FAST               11 (a)\n",
      "            232 BINARY_SUBTRACT\n",
      "            234 BINARY_MULTIPLY\n",
      "            236 BINARY_ADD\n",
      "            238 LOAD_FAST                5 (prev)\n",
      "            240 LOAD_FAST                7 (v)\n",
      "            242 STORE_SUBSCR\n",
      "            244 JUMP_ABSOLUTE          124\n",
      "        >>  246 JUMP_ABSOLUTE           64\n",
      "\n",
      " 28     >>  248 LOAD_FAST                4 (dist)\n",
      "            250 LOAD_FAST                5 (prev)\n",
      "            252 BUILD_TUPLE              2\n",
      "            254 RETURN_VALUE\n"
     ]
    }
   ],
   "source": [
    "dis.dis(dijkstra_p)"
   ]
  },
  {
   "cell_type": "code",
   "execution_count": 21,
   "id": "b0a486b1",
   "metadata": {},
   "outputs": [
    {
     "name": "stdout",
     "output_type": "stream",
     "text": [
      "  2           0 LOAD_GLOBAL              0 (np)\n",
      "              2 LOAD_METHOD              1 (array)\n",
      "              4 LOAD_CONST               1 (1000000000.0)\n",
      "              6 BUILD_LIST               1\n",
      "              8 LOAD_GLOBAL              2 (len)\n",
      "             10 LOAD_FAST                0 (verts)\n",
      "             12 CALL_FUNCTION            1\n",
      "             14 BINARY_MULTIPLY\n",
      "             16 CALL_METHOD              1\n",
      "             18 STORE_FAST               4 (dist)\n",
      "\n",
      "  3          20 LOAD_GLOBAL              0 (np)\n",
      "             22 LOAD_METHOD              1 (array)\n",
      "             24 LOAD_CONST               2 (-1)\n",
      "             26 BUILD_LIST               1\n",
      "             28 LOAD_GLOBAL              2 (len)\n",
      "             30 LOAD_FAST                0 (verts)\n",
      "             32 CALL_FUNCTION            1\n",
      "             34 BINARY_MULTIPLY\n",
      "             36 CALL_METHOD              1\n",
      "             38 STORE_FAST               5 (prev)\n",
      "\n",
      "  4          40 LOAD_CONST               3 (0)\n",
      "             42 LOAD_FAST                4 (dist)\n",
      "             44 LOAD_FAST                2 (source)\n",
      "             46 STORE_SUBSCR\n",
      "\n",
      "  5          48 LOAD_CONST               3 (0)\n",
      "             50 LOAD_FAST                2 (source)\n",
      "             52 BUILD_TUPLE              2\n",
      "             54 BUILD_LIST               1\n",
      "             56 STORE_FAST               6 (Q)\n",
      "\n",
      "  6     >>   58 LOAD_GLOBAL              2 (len)\n",
      "             60 LOAD_FAST                6 (Q)\n",
      "             62 CALL_FUNCTION            1\n",
      "             64 POP_JUMP_IF_FALSE      188\n",
      "\n",
      "  7          66 LOAD_GLOBAL              3 (heappop)\n",
      "             68 LOAD_FAST                6 (Q)\n",
      "             70 CALL_FUNCTION            1\n",
      "             72 LOAD_CONST               4 (1)\n",
      "             74 BINARY_SUBSCR\n",
      "             76 STORE_FAST               7 (u)\n",
      "\n",
      "  8          78 LOAD_FAST                7 (u)\n",
      "             80 LOAD_FAST                3 (target)\n",
      "             82 COMPARE_OP               2 (==)\n",
      "             84 POP_JUMP_IF_FALSE       94\n",
      "\n",
      "  9          86 LOAD_FAST                4 (dist)\n",
      "             88 LOAD_FAST                5 (prev)\n",
      "             90 BUILD_TUPLE              2\n",
      "             92 RETURN_VALUE\n",
      "\n",
      " 10     >>   94 LOAD_FAST                1 (edges)\n",
      "             96 LOAD_FAST                7 (u)\n",
      "             98 BINARY_SUBSCR\n",
      "            100 GET_ITER\n",
      "        >>  102 FOR_ITER                82 (to 186)\n",
      "            104 STORE_FAST               8 (v)\n",
      "\n",
      " 11         106 LOAD_FAST                4 (dist)\n",
      "            108 LOAD_FAST                7 (u)\n",
      "            110 BINARY_SUBSCR\n",
      "            112 LOAD_GLOBAL              0 (np)\n",
      "            114 LOAD_ATTR                4 (linalg)\n",
      "            116 LOAD_METHOD              5 (norm)\n",
      "            118 LOAD_FAST                0 (verts)\n",
      "            120 LOAD_FAST                7 (u)\n",
      "            122 BINARY_SUBSCR\n",
      "            124 LOAD_FAST                0 (verts)\n",
      "            126 LOAD_FAST                8 (v)\n",
      "            128 BINARY_SUBSCR\n",
      "            130 BINARY_SUBTRACT\n",
      "            132 CALL_METHOD              1\n",
      "            134 BINARY_ADD\n",
      "            136 STORE_FAST               9 (alt)\n",
      "\n",
      " 12         138 LOAD_FAST                9 (alt)\n",
      "            140 LOAD_FAST                4 (dist)\n",
      "            142 LOAD_FAST                8 (v)\n",
      "            144 BINARY_SUBSCR\n",
      "            146 COMPARE_OP               0 (<)\n",
      "            148 POP_JUMP_IF_FALSE      102\n",
      "\n",
      " 13         150 LOAD_FAST                9 (alt)\n",
      "            152 LOAD_FAST                4 (dist)\n",
      "            154 LOAD_FAST                8 (v)\n",
      "            156 STORE_SUBSCR\n",
      "\n",
      " 14         158 LOAD_FAST                7 (u)\n",
      "            160 LOAD_FAST                5 (prev)\n",
      "            162 LOAD_FAST                8 (v)\n",
      "            164 STORE_SUBSCR\n",
      "\n",
      " 15         166 LOAD_GLOBAL              6 (heappush)\n",
      "            168 LOAD_FAST                6 (Q)\n",
      "            170 LOAD_FAST                4 (dist)\n",
      "            172 LOAD_FAST                8 (v)\n",
      "            174 BINARY_SUBSCR\n",
      "            176 LOAD_FAST                8 (v)\n",
      "            178 BUILD_TUPLE              2\n",
      "            180 CALL_FUNCTION            2\n",
      "            182 POP_TOP\n",
      "            184 JUMP_ABSOLUTE          102\n",
      "        >>  186 JUMP_ABSOLUTE           58\n",
      "\n",
      " 16     >>  188 LOAD_FAST                4 (dist)\n",
      "            190 LOAD_FAST                5 (prev)\n",
      "            192 BUILD_TUPLE              2\n",
      "            194 RETURN_VALUE\n"
     ]
    }
   ],
   "source": [
    "dis.dis(dijkstra_pq)"
   ]
  },
  {
   "cell_type": "code",
   "execution_count": 22,
   "id": "3ce9ee3e",
   "metadata": {},
   "outputs": [
    {
     "name": "stdout",
     "output_type": "stream",
     "text": [
      " 11           0 LOAD_GLOBAL              0 (Dict)\n",
      "              2 LOAD_ATTR                1 (empty)\n",
      "\n",
      " 12           4 LOAD_GLOBAL              2 (types)\n",
      "              6 LOAD_ATTR                3 (i8)\n",
      "\n",
      " 13           8 LOAD_GLOBAL              2 (types)\n",
      "             10 LOAD_ATTR                4 (f8)\n",
      "\n",
      " 11          12 LOAD_CONST               1 (('key_type', 'value_type'))\n",
      "             14 CALL_FUNCTION_KW         2\n",
      "             16 STORE_FAST               4 (dist)\n",
      "\n",
      " 15          18 LOAD_GLOBAL              0 (Dict)\n",
      "             20 LOAD_ATTR                1 (empty)\n",
      "\n",
      " 16          22 LOAD_GLOBAL              2 (types)\n",
      "             24 LOAD_ATTR                3 (i8)\n",
      "\n",
      " 17          26 LOAD_GLOBAL              2 (types)\n",
      "             28 LOAD_ATTR                3 (i8)\n",
      "\n",
      " 15          30 LOAD_CONST               1 (('key_type', 'value_type'))\n",
      "             32 CALL_FUNCTION_KW         2\n",
      "             34 STORE_FAST               5 (prev)\n",
      "\n",
      " 19          36 LOAD_GLOBAL              5 (list)\n",
      "             38 LOAD_GLOBAL              6 (range)\n",
      "             40 LOAD_GLOBAL              7 (len)\n",
      "             42 LOAD_FAST                0 (verts)\n",
      "             44 CALL_FUNCTION            1\n",
      "             46 CALL_FUNCTION            1\n",
      "             48 CALL_FUNCTION            1\n",
      "             50 STORE_FAST               6 (Q)\n",
      "\n",
      " 20          52 LOAD_FAST                6 (Q)\n",
      "             54 GET_ITER\n",
      "        >>   56 FOR_ITER                32 (to 90)\n",
      "             58 STORE_FAST               7 (v)\n",
      "\n",
      " 21          60 LOAD_GLOBAL              8 (np)\n",
      "             62 LOAD_METHOD              9 (float)\n",
      "             64 LOAD_CONST               2 (1000000000.0)\n",
      "             66 CALL_METHOD              1\n",
      "             68 LOAD_FAST                4 (dist)\n",
      "             70 LOAD_FAST                7 (v)\n",
      "             72 STORE_SUBSCR\n",
      "\n",
      " 22          74 LOAD_GLOBAL              8 (np)\n",
      "             76 LOAD_METHOD             10 (int64)\n",
      "             78 LOAD_CONST               3 (-1)\n",
      "             80 CALL_METHOD              1\n",
      "             82 LOAD_FAST                5 (prev)\n",
      "             84 LOAD_FAST                7 (v)\n",
      "             86 STORE_SUBSCR\n",
      "             88 JUMP_ABSOLUTE           56\n",
      "\n",
      " 23     >>   90 LOAD_CONST               4 (0)\n",
      "             92 LOAD_FAST                4 (dist)\n",
      "             94 LOAD_FAST                2 (source)\n",
      "             96 STORE_SUBSCR\n",
      "\n",
      " 24     >>   98 LOAD_GLOBAL              7 (len)\n",
      "            100 LOAD_FAST                6 (Q)\n",
      "            102 CALL_FUNCTION            1\n",
      "            104 EXTENDED_ARG             1\n",
      "            106 POP_JUMP_IF_FALSE      284\n",
      "\n",
      " 25         108 LOAD_GLOBAL             11 (get_mindist_c)\n",
      "            110 LOAD_FAST                4 (dist)\n",
      "            112 LOAD_FAST                6 (Q)\n",
      "            114 CALL_FUNCTION            2\n",
      "            116 STORE_FAST               8 (u)\n",
      "\n",
      " 26         118 LOAD_FAST                6 (Q)\n",
      "            120 LOAD_METHOD             12 (remove)\n",
      "            122 LOAD_FAST                8 (u)\n",
      "            124 CALL_METHOD              1\n",
      "            126 POP_TOP\n",
      "\n",
      " 27         128 LOAD_FAST                8 (u)\n",
      "            130 LOAD_FAST                3 (target)\n",
      "            132 COMPARE_OP               2 (==)\n",
      "            134 POP_JUMP_IF_FALSE      144\n",
      "\n",
      " 28         136 LOAD_FAST                4 (dist)\n",
      "            138 LOAD_FAST                5 (prev)\n",
      "            140 BUILD_TUPLE              2\n",
      "            142 RETURN_VALUE\n",
      "\n",
      " 29     >>  144 LOAD_GLOBAL              6 (range)\n",
      "            146 LOAD_GLOBAL              7 (len)\n",
      "            148 LOAD_FAST                1 (edges)\n",
      "            150 LOAD_FAST                8 (u)\n",
      "            152 BINARY_SUBSCR\n",
      "            154 CALL_FUNCTION            1\n",
      "            156 CALL_FUNCTION            1\n",
      "            158 GET_ITER\n",
      "        >>  160 FOR_ITER               120 (to 282)\n",
      "            162 STORE_FAST               9 (i)\n",
      "\n",
      " 30         164 LOAD_FAST                1 (edges)\n",
      "            166 LOAD_FAST                8 (u)\n",
      "            168 BINARY_SUBSCR\n",
      "            170 LOAD_FAST                9 (i)\n",
      "            172 BINARY_SUBSCR\n",
      "            174 STORE_FAST               7 (v)\n",
      "\n",
      " 31         176 LOAD_FAST                4 (dist)\n",
      "            178 LOAD_FAST                8 (u)\n",
      "            180 BINARY_SUBSCR\n",
      "            182 LOAD_GLOBAL              8 (np)\n",
      "            184 LOAD_ATTR               13 (linalg)\n",
      "            186 LOAD_METHOD             14 (norm)\n",
      "            188 LOAD_FAST                0 (verts)\n",
      "            190 LOAD_FAST                8 (u)\n",
      "            192 BINARY_SUBSCR\n",
      "            194 LOAD_FAST                0 (verts)\n",
      "            196 LOAD_FAST                7 (v)\n",
      "            198 BINARY_SUBSCR\n",
      "            200 BINARY_SUBTRACT\n",
      "            202 CALL_METHOD              1\n",
      "            204 BINARY_ADD\n",
      "            206 STORE_FAST              10 (alt)\n",
      "\n",
      " 32         208 LOAD_GLOBAL             15 (boolean)\n",
      "            210 LOAD_FAST               10 (alt)\n",
      "            212 LOAD_FAST                4 (dist)\n",
      "            214 LOAD_FAST                7 (v)\n",
      "            216 BINARY_SUBSCR\n",
      "            218 COMPARE_OP               0 (<)\n",
      "            220 CALL_FUNCTION            1\n",
      "            222 STORE_FAST              11 (a)\n",
      "\n",
      " 33         224 LOAD_FAST               10 (alt)\n",
      "            226 LOAD_FAST               11 (a)\n",
      "            228 BINARY_MULTIPLY\n",
      "            230 LOAD_FAST                4 (dist)\n",
      "            232 LOAD_FAST                7 (v)\n",
      "            234 BINARY_SUBSCR\n",
      "            236 LOAD_CONST               5 (1)\n",
      "            238 LOAD_FAST               11 (a)\n",
      "            240 BINARY_SUBTRACT\n",
      "            242 BINARY_MULTIPLY\n",
      "            244 BINARY_ADD\n",
      "            246 LOAD_FAST                4 (dist)\n",
      "            248 LOAD_FAST                7 (v)\n",
      "            250 STORE_SUBSCR\n",
      "\n",
      " 34         252 LOAD_FAST                8 (u)\n",
      "            254 LOAD_FAST               11 (a)\n",
      "            256 BINARY_MULTIPLY\n",
      "            258 LOAD_FAST                5 (prev)\n",
      "            260 LOAD_FAST                7 (v)\n",
      "            262 BINARY_SUBSCR\n",
      "            264 LOAD_CONST               5 (1)\n",
      "            266 LOAD_FAST               11 (a)\n",
      "            268 BINARY_SUBTRACT\n",
      "            270 BINARY_MULTIPLY\n",
      "            272 BINARY_ADD\n",
      "            274 LOAD_FAST                5 (prev)\n",
      "            276 LOAD_FAST                7 (v)\n",
      "            278 STORE_SUBSCR\n",
      "            280 JUMP_ABSOLUTE          160\n",
      "        >>  282 JUMP_ABSOLUTE           98\n",
      "\n",
      " 35     >>  284 LOAD_FAST                4 (dist)\n",
      "            286 LOAD_FAST                5 (prev)\n",
      "            288 BUILD_TUPLE              2\n",
      "            290 RETURN_VALUE\n"
     ]
    }
   ],
   "source": [
    "dis.dis(dijkstra_c)"
   ]
  },
  {
   "cell_type": "code",
   "execution_count": 23,
   "id": "2daea763",
   "metadata": {},
   "outputs": [
    {
     "name": "stdout",
     "output_type": "stream",
     "text": [
      "  3           0 LOAD_GLOBAL              0 (np)\n",
      "              2 LOAD_METHOD              1 (array)\n",
      "              4 LOAD_GLOBAL              0 (np)\n",
      "              6 LOAD_METHOD              2 (float64)\n",
      "              8 LOAD_CONST               1 (1000000000.0)\n",
      "             10 CALL_METHOD              1\n",
      "             12 BUILD_LIST               1\n",
      "             14 LOAD_GLOBAL              3 (len)\n",
      "             16 LOAD_FAST                0 (verts)\n",
      "             18 CALL_FUNCTION            1\n",
      "             20 BINARY_MULTIPLY\n",
      "             22 CALL_METHOD              1\n",
      "             24 STORE_FAST               4 (dist)\n",
      "\n",
      "  4          26 LOAD_GLOBAL              0 (np)\n",
      "             28 LOAD_METHOD              1 (array)\n",
      "             30 LOAD_CONST               2 (-1)\n",
      "             32 BUILD_LIST               1\n",
      "             34 LOAD_GLOBAL              3 (len)\n",
      "             36 LOAD_FAST                0 (verts)\n",
      "             38 CALL_FUNCTION            1\n",
      "             40 BINARY_MULTIPLY\n",
      "             42 CALL_METHOD              1\n",
      "             44 STORE_FAST               5 (prev)\n",
      "\n",
      "  5          46 LOAD_GLOBAL              0 (np)\n",
      "             48 LOAD_METHOD              2 (float64)\n",
      "             50 LOAD_CONST               3 (0)\n",
      "             52 CALL_METHOD              1\n",
      "             54 LOAD_FAST                4 (dist)\n",
      "             56 LOAD_FAST                2 (source)\n",
      "             58 STORE_SUBSCR\n",
      "\n",
      "  6          60 LOAD_GLOBAL              0 (np)\n",
      "             62 LOAD_METHOD              2 (float64)\n",
      "             64 LOAD_CONST               3 (0)\n",
      "             66 CALL_METHOD              1\n",
      "             68 LOAD_FAST                2 (source)\n",
      "             70 BUILD_TUPLE              2\n",
      "             72 BUILD_LIST               1\n",
      "             74 STORE_FAST               6 (Q)\n",
      "\n",
      "  7     >>   76 LOAD_GLOBAL              3 (len)\n",
      "             78 LOAD_FAST                6 (Q)\n",
      "             80 CALL_FUNCTION            1\n",
      "             82 POP_JUMP_IF_FALSE      206\n",
      "\n",
      "  8          84 LOAD_GLOBAL              4 (heappop)\n",
      "             86 LOAD_FAST                6 (Q)\n",
      "             88 CALL_FUNCTION            1\n",
      "             90 LOAD_CONST               4 (1)\n",
      "             92 BINARY_SUBSCR\n",
      "             94 STORE_FAST               7 (u)\n",
      "\n",
      "  9          96 LOAD_FAST                7 (u)\n",
      "             98 LOAD_FAST                3 (target)\n",
      "            100 COMPARE_OP               2 (==)\n",
      "            102 POP_JUMP_IF_FALSE      112\n",
      "\n",
      " 10         104 LOAD_FAST                4 (dist)\n",
      "            106 LOAD_FAST                5 (prev)\n",
      "            108 BUILD_TUPLE              2\n",
      "            110 RETURN_VALUE\n",
      "\n",
      " 11     >>  112 LOAD_FAST                1 (edges)\n",
      "            114 LOAD_FAST                7 (u)\n",
      "            116 BINARY_SUBSCR\n",
      "            118 GET_ITER\n",
      "        >>  120 FOR_ITER                82 (to 204)\n",
      "            122 STORE_FAST               8 (v)\n",
      "\n",
      " 12         124 LOAD_FAST                4 (dist)\n",
      "            126 LOAD_FAST                7 (u)\n",
      "            128 BINARY_SUBSCR\n",
      "            130 LOAD_GLOBAL              0 (np)\n",
      "            132 LOAD_ATTR                5 (linalg)\n",
      "            134 LOAD_METHOD              6 (norm)\n",
      "            136 LOAD_FAST                0 (verts)\n",
      "            138 LOAD_FAST                7 (u)\n",
      "            140 BINARY_SUBSCR\n",
      "            142 LOAD_FAST                0 (verts)\n",
      "            144 LOAD_FAST                8 (v)\n",
      "            146 BINARY_SUBSCR\n",
      "            148 BINARY_SUBTRACT\n",
      "            150 CALL_METHOD              1\n",
      "            152 BINARY_ADD\n",
      "            154 STORE_FAST               9 (alt)\n",
      "\n",
      " 13         156 LOAD_FAST                9 (alt)\n",
      "            158 LOAD_FAST                4 (dist)\n",
      "            160 LOAD_FAST                8 (v)\n",
      "            162 BINARY_SUBSCR\n",
      "            164 COMPARE_OP               0 (<)\n",
      "            166 POP_JUMP_IF_FALSE      120\n",
      "\n",
      " 14         168 LOAD_FAST                9 (alt)\n",
      "            170 LOAD_FAST                4 (dist)\n",
      "            172 LOAD_FAST                8 (v)\n",
      "            174 STORE_SUBSCR\n",
      "\n",
      " 15         176 LOAD_FAST                7 (u)\n",
      "            178 LOAD_FAST                5 (prev)\n",
      "            180 LOAD_FAST                8 (v)\n",
      "            182 STORE_SUBSCR\n",
      "\n",
      " 16         184 LOAD_GLOBAL              7 (heappush)\n",
      "            186 LOAD_FAST                6 (Q)\n",
      "            188 LOAD_FAST                4 (dist)\n",
      "            190 LOAD_FAST                8 (v)\n",
      "            192 BINARY_SUBSCR\n",
      "            194 LOAD_FAST                8 (v)\n",
      "            196 BUILD_TUPLE              2\n",
      "            198 CALL_FUNCTION            2\n",
      "            200 POP_TOP\n",
      "            202 JUMP_ABSOLUTE          120\n",
      "        >>  204 JUMP_ABSOLUTE           76\n",
      "\n",
      " 17     >>  206 LOAD_FAST                4 (dist)\n",
      "            208 LOAD_FAST                5 (prev)\n",
      "            210 BUILD_TUPLE              2\n",
      "            212 RETURN_VALUE\n"
     ]
    }
   ],
   "source": [
    "dis.dis(dijkstra_cq)"
   ]
  },
  {
   "cell_type": "code",
   "execution_count": null,
   "id": "6ecf1733",
   "metadata": {},
   "outputs": [],
   "source": [
    "times2_pq[0]/times2_cq[0]"
   ]
  },
  {
   "cell_type": "code",
   "execution_count": null,
   "id": "47194a17",
   "metadata": {},
   "outputs": [],
   "source": []
  }
 ],
 "metadata": {
  "kernelspec": {
   "display_name": "Python 3",
   "language": "python",
   "name": "python3"
  },
  "language_info": {
   "codemirror_mode": {
    "name": "ipython",
    "version": 3
   },
   "file_extension": ".py",
   "mimetype": "text/x-python",
   "name": "python",
   "nbconvert_exporter": "python",
   "pygments_lexer": "ipython3",
   "version": "3.8.8"
  }
 },
 "nbformat": 4,
 "nbformat_minor": 5
}
